{
"meta":{"test_sets":[],"test_metrics":[],"learn_metrics":[{"best_value":"Min","name":"RMSE"}],"launch_mode":"Train","parameters":"","iteration_count":1000,"learn_sets":["learn"],"name":"experiment"},
"iterations":[
{"learn":[0.9940915897],"iteration":0,"passed_time":0.05303796405,"remaining_time":52.98492609},
{"learn":[0.9895428784],"iteration":1,"passed_time":0.05807168547,"remaining_time":28.97777105},
{"learn":[0.984989628],"iteration":2,"passed_time":0.06157613659,"remaining_time":20.46380273},
{"learn":[0.9804202078],"iteration":3,"passed_time":0.06489688761,"remaining_time":16.15932502},
{"learn":[0.9759528253],"iteration":4,"passed_time":0.06770904873,"remaining_time":13.4741007},
{"learn":[0.9716072528],"iteration":5,"passed_time":0.07130626765,"remaining_time":11.81307167},
{"learn":[0.9671390196],"iteration":6,"passed_time":0.07512205122,"remaining_time":10.65659955},
{"learn":[0.9629175979],"iteration":7,"passed_time":0.07877960503,"remaining_time":9.768671024},
{"learn":[0.9586904476],"iteration":8,"passed_time":0.08139513338,"remaining_time":8.962508576},
{"learn":[0.9543750166],"iteration":9,"passed_time":0.0840943129,"remaining_time":8.325336977},
{"learn":[0.9500608461],"iteration":10,"passed_time":0.08682543769,"remaining_time":7.806396171},
{"learn":[0.945753831],"iteration":11,"passed_time":0.08939072996,"remaining_time":7.359836767},
{"learn":[0.9416907796],"iteration":12,"passed_time":0.09188371479,"remaining_time":6.976094346},
{"learn":[0.9376394936],"iteration":13,"passed_time":0.09450617369,"remaining_time":6.655934804},
{"learn":[0.933638154],"iteration":14,"passed_time":0.09829231964,"remaining_time":6.45452899},
{"learn":[0.9296859689],"iteration":15,"passed_time":0.1016549388,"remaining_time":6.251778735},
{"learn":[0.9257543503],"iteration":16,"passed_time":0.1047793322,"remaining_time":6.058710797},
{"learn":[0.9218293156],"iteration":17,"passed_time":0.1077464391,"remaining_time":5.878166844},
{"learn":[0.9178592904],"iteration":18,"passed_time":0.1104497315,"remaining_time":5.702694031},
{"learn":[0.9137694496],"iteration":19,"passed_time":0.1127616287,"remaining_time":5.525319804},
{"learn":[0.9100084886],"iteration":20,"passed_time":0.1157117234,"remaining_time":5.394370344},
{"learn":[0.9060543303],"iteration":21,"passed_time":0.1181750445,"remaining_time":5.253417885},
{"learn":[0.9020944274],"iteration":22,"passed_time":0.1206645256,"remaining_time":5.125619196},
{"learn":[0.8982761412],"iteration":23,"passed_time":0.1228839012,"remaining_time":4.997278649},
{"learn":[0.8944353262],"iteration":24,"passed_time":0.1251451704,"remaining_time":4.880661645},
{"learn":[0.8905160235],"iteration":25,"passed_time":0.1273855656,"remaining_time":4.772059265},
{"learn":[0.8870190988],"iteration":26,"passed_time":0.1297158472,"remaining_time":4.674574791},
{"learn":[0.8833189045],"iteration":27,"passed_time":0.1320905519,"remaining_time":4.585429159},
{"learn":[0.8797845816],"iteration":28,"passed_time":0.1343963237,"remaining_time":4.499959665},
{"learn":[0.8763133808],"iteration":29,"passed_time":0.1387199106,"remaining_time":4.485277109},
{"learn":[0.8727578722],"iteration":30,"passed_time":0.1419279404,"remaining_time":4.436392717},
{"learn":[0.8690541594],"iteration":31,"passed_time":0.1445766062,"remaining_time":4.373442338},
{"learn":[0.86541455],"iteration":32,"passed_time":0.1468526074,"remaining_time":4.303226406},
{"learn":[0.8619880309],"iteration":33,"passed_time":0.1490854085,"remaining_time":4.235779547},
{"learn":[0.8583502775],"iteration":34,"passed_time":0.1515097387,"remaining_time":4.177339938},
{"learn":[0.8549409267],"iteration":35,"passed_time":0.1538089363,"remaining_time":4.118661517},
{"learn":[0.8516202878],"iteration":36,"passed_time":0.1566481646,"remaining_time":4.077086015},
{"learn":[0.8484382527],"iteration":37,"passed_time":0.1595765314,"remaining_time":4.039805874},
{"learn":[0.8450800849],"iteration":38,"passed_time":0.1621852363,"remaining_time":3.996410566},
{"learn":[0.8418021311],"iteration":39,"passed_time":0.1649996565,"remaining_time":3.959991756},
{"learn":[0.8384879487],"iteration":40,"passed_time":0.1677671831,"remaining_time":3.924115333},
{"learn":[0.8351600934],"iteration":41,"passed_time":0.1706746511,"remaining_time":3.893007519},
{"learn":[0.8319294572],"iteration":42,"passed_time":0.1736514102,"remaining_time":3.864753478},
{"learn":[0.828711798],"iteration":43,"passed_time":0.1758697823,"remaining_time":3.821170724},
{"learn":[0.825377224],"iteration":44,"passed_time":0.1798191855,"remaining_time":3.816162715},
{"learn":[0.8222842224],"iteration":45,"passed_time":0.1824708967,"remaining_time":3.784287727},
{"learn":[0.8191758154],"iteration":46,"passed_time":0.1854536623,"remaining_time":3.760368941},
{"learn":[0.8161346066],"iteration":47,"passed_time":0.1880755382,"remaining_time":3.730164841},
{"learn":[0.8129652583],"iteration":48,"passed_time":0.1908710367,"remaining_time":3.704456243},
{"learn":[0.8097761922],"iteration":49,"passed_time":0.1934840102,"remaining_time":3.676196193},
{"learn":[0.8068153258],"iteration":50,"passed_time":0.1977514553,"remaining_time":3.679728061},
{"learn":[0.8037923722],"iteration":51,"passed_time":0.20128495,"remaining_time":3.669579473},
{"learn":[0.8009301912],"iteration":52,"passed_time":0.2042529974,"remaining_time":3.649577142},
{"learn":[0.7980257059],"iteration":53,"passed_time":0.2069531019,"remaining_time":3.625511748},
{"learn":[0.7950107807],"iteration":54,"passed_time":0.2093991343,"remaining_time":3.597857852},
{"learn":[0.7921119714],"iteration":55,"passed_time":0.2117682838,"remaining_time":3.569808213},
{"learn":[0.7893072002],"iteration":56,"passed_time":0.2141214898,"remaining_time":3.542395876},
{"learn":[0.7863388164],"iteration":57,"passed_time":0.2178157165,"remaining_time":3.537627672},
{"learn":[0.7835464172],"iteration":58,"passed_time":0.2207801752,"remaining_time":3.521256692},
{"learn":[0.7806056761],"iteration":59,"passed_time":0.2240709005,"remaining_time":3.510444107},
{"learn":[0.7778354631],"iteration":60,"passed_time":0.2269517217,"remaining_time":3.493568307},
{"learn":[0.7751395532],"iteration":61,"passed_time":0.2298315712,"remaining_time":3.477129254},
{"learn":[0.7725143473],"iteration":62,"passed_time":0.2330618927,"remaining_time":3.46633323},
{"learn":[0.7698404779],"iteration":63,"passed_time":0.2369788293,"remaining_time":3.465815378},
{"learn":[0.7671053989],"iteration":64,"passed_time":0.2402988988,"remaining_time":3.456607236},
{"learn":[0.7644084721],"iteration":65,"passed_time":0.2427628373,"remaining_time":3.43546197},
{"learn":[0.7617943508],"iteration":66,"passed_time":0.2450622302,"remaining_time":3.412582996},
{"learn":[0.7590940007],"iteration":67,"passed_time":0.247382777,"remaining_time":3.390599238},
{"learn":[0.756440181],"iteration":68,"passed_time":0.2497617688,"remaining_time":3.369974011},
{"learn":[0.7537724681],"iteration":69,"passed_time":0.2518565553,"remaining_time":3.346094235},
{"learn":[0.7511912592],"iteration":70,"passed_time":0.2545787384,"remaining_time":3.331037295},
{"learn":[0.7486517852],"iteration":71,"passed_time":0.2590499276,"remaining_time":3.338865734},
{"learn":[0.7461642274],"iteration":72,"passed_time":0.2629396847,"remaining_time":3.338973805},
{"learn":[0.7435736988],"iteration":73,"passed_time":0.2660839255,"remaining_time":3.329644798},
{"learn":[0.7410620039],"iteration":74,"passed_time":0.2688699844,"remaining_time":3.316063141},
{"learn":[0.7387434877],"iteration":75,"passed_time":0.2714980883,"remaining_time":3.300845179},
{"learn":[0.7362467666],"iteration":76,"passed_time":0.2744475356,"remaining_time":3.289806174},
{"learn":[0.7336705124],"iteration":77,"passed_time":0.2769977177,"remaining_time":3.274255074},
{"learn":[0.7311406805],"iteration":78,"passed_time":0.2793805197,"remaining_time":3.257081755},
{"learn":[0.7288389033],"iteration":79,"passed_time":0.2813767308,"remaining_time":3.235832405},
{"learn":[0.7264451313],"iteration":80,"passed_time":0.2834688691,"remaining_time":3.216146798},
{"learn":[0.7241981119],"iteration":81,"passed_time":0.2856515119,"remaining_time":3.197903511},
{"learn":[0.7219437817],"iteration":82,"passed_time":0.2881579793,"remaining_time":3.183624904},
{"learn":[0.7196268086],"iteration":83,"passed_time":0.2908057071,"remaining_time":3.171166997},
{"learn":[0.7174342294],"iteration":84,"passed_time":0.2940430677,"remaining_time":3.16528714},
{"learn":[0.7152391659],"iteration":85,"passed_time":0.2982440704,"remaining_time":3.169710237},
{"learn":[0.7129891953],"iteration":86,"passed_time":0.3015798231,"remaining_time":3.164854925},
{"learn":[0.7108276187],"iteration":87,"passed_time":0.3046367985,"remaining_time":3.157145003},
{"learn":[0.7085491715],"iteration":88,"passed_time":0.3070888757,"remaining_time":3.14334793},
{"learn":[0.7063116629],"iteration":89,"passed_time":0.3093149952,"remaining_time":3.127518285},
{"learn":[0.7039971229],"iteration":90,"passed_time":0.3123283524,"remaining_time":3.119851344},
{"learn":[0.7017831443],"iteration":91,"passed_time":0.3156622,"remaining_time":3.11544867},
{"learn":[0.6994737817],"iteration":92,"passed_time":0.3180924696,"remaining_time":3.102256666},
{"learn":[0.6973045918],"iteration":93,"passed_time":0.3207444381,"remaining_time":3.091430435},
{"learn":[0.6951018628],"iteration":94,"passed_time":0.3236385901,"remaining_time":3.083083411},
{"learn":[0.6929189392],"iteration":95,"passed_time":0.326356599,"remaining_time":3.073191307},
{"learn":[0.6908098552],"iteration":96,"passed_time":0.3293037941,"remaining_time":3.065580682},
{"learn":[0.6886991978],"iteration":97,"passed_time":0.331759095,"remaining_time":3.053537793},
{"learn":[0.6864802902],"iteration":98,"passed_time":0.3351926513,"remaining_time":3.050591706},
{"learn":[0.6843832329],"iteration":99,"passed_time":0.3380656959,"remaining_time":3.042591263},
{"learn":[0.6823881734],"iteration":100,"passed_time":0.3402413889,"remaining_time":3.028485234},
{"learn":[0.6804409969],"iteration":101,"passed_time":0.3426591422,"remaining_time":3.016744213},
{"learn":[0.678370194],"iteration":102,"passed_time":0.3447307388,"remaining_time":3.002169638},
{"learn":[0.6763726259],"iteration":103,"passed_time":0.3470801622,"remaining_time":2.990229089},
{"learn":[0.6744137794],"iteration":104,"passed_time":0.349268855,"remaining_time":2.977101192},
{"learn":[0.6724274227],"iteration":105,"passed_time":0.3516192595,"remaining_time":2.965543566},
{"learn":[0.6705322665],"iteration":106,"passed_time":0.355021914,"remaining_time":2.962939899},
{"learn":[0.6686740108],"iteration":107,"passed_time":0.3577460159,"remaining_time":2.954717094},
{"learn":[0.6666385058],"iteration":108,"passed_time":0.3607133866,"remaining_time":2.948583738},
{"learn":[0.6647084587],"iteration":109,"passed_time":0.36362696,"remaining_time":2.942072677},
{"learn":[0.6628137724],"iteration":110,"passed_time":0.3658987175,"remaining_time":2.930486125},
{"learn":[0.6609054751],"iteration":111,"passed_time":0.3680832055,"remaining_time":2.918373986},
{"learn":[0.6589957089],"iteration":112,"passed_time":0.3701077725,"remaining_time":2.905182249},
{"learn":[0.6571261471],"iteration":113,"passed_time":0.3719679164,"remaining_time":2.890908544},
{"learn":[0.6552837778],"iteration":114,"passed_time":0.3754648963,"remaining_time":2.889447246},
{"learn":[0.6534604234],"iteration":115,"passed_time":0.3788298459,"remaining_time":2.886944687},
{"learn":[0.6515581489],"iteration":116,"passed_time":0.3815116138,"remaining_time":2.87927141},
{"learn":[0.6497562525],"iteration":117,"passed_time":0.3839175467,"remaining_time":2.869620985},
{"learn":[0.6479967097],"iteration":118,"passed_time":0.386519331,"remaining_time":2.861542274},
{"learn":[0.6463191125],"iteration":119,"passed_time":0.3890177191,"remaining_time":2.852796607},
{"learn":[0.6445755401],"iteration":120,"passed_time":0.3920827478,"remaining_time":2.84827054},
{"learn":[0.6428524216],"iteration":121,"passed_time":0.39597779,"remaining_time":2.8497418},
{"learn":[0.6410742469],"iteration":122,"passed_time":0.3985331481,"remaining_time":2.841573747},
{"learn":[0.6392808858],"iteration":123,"passed_time":0.4007854225,"remaining_time":2.831355082},
{"learn":[0.6375851485],"iteration":124,"passed_time":0.4028056817,"remaining_time":2.819639772},
{"learn":[0.6358212418],"iteration":125,"passed_time":0.4049534999,"remaining_time":2.808963166},
{"learn":[0.6341733227],"iteration":126,"passed_time":0.4073728959,"remaining_time":2.800287701},
{"learn":[0.6325138265],"iteration":127,"passed_time":0.409396262,"remaining_time":2.789012035},
{"learn":[0.6308454214],"iteration":128,"passed_time":0.4115654966,"remaining_time":2.778864709},
{"learn":[0.6292591978],"iteration":129,"passed_time":0.4151308043,"remaining_time":2.778183075},
{"learn":[0.627583166],"iteration":130,"passed_time":0.4183803936,"remaining_time":2.775363069},
{"learn":[0.6259273392],"iteration":131,"passed_time":0.4210452286,"remaining_time":2.768691352},
{"learn":[0.6242338707],"iteration":132,"passed_time":0.4239345811,"remaining_time":2.763543472},
{"learn":[0.6227138011],"iteration":133,"passed_time":0.4256579313,"remaining_time":2.750893795},
{"learn":[0.6210304902],"iteration":134,"passed_time":0.4283348948,"remaining_time":2.744516178},
{"learn":[0.6195095287],"iteration":135,"passed_time":0.4303824251,"remaining_time":2.73419423},
{"learn":[0.6179511183],"iteration":136,"passed_time":0.4326406424,"remaining_time":2.725320251},
{"learn":[0.6163568466],"iteration":137,"passed_time":0.4355697795,"remaining_time":2.720732971},
{"learn":[0.6147600951],"iteration":138,"passed_time":0.4379297838,"remaining_time":2.712644201},
{"learn":[0.6131925524],"iteration":139,"passed_time":0.4401919921,"remaining_time":2.704036523},
{"learn":[0.6116399746],"iteration":140,"passed_time":0.4425823125,"remaining_time":2.696299336},
{"learn":[0.6100540219],"iteration":141,"passed_time":0.4446407818,"remaining_time":2.68663233},
{"learn":[0.6084803863],"iteration":142,"passed_time":0.4467377072,"remaining_time":2.677302203},
{"learn":[0.6070232533],"iteration":143,"passed_time":0.4493566642,"remaining_time":2.671175726},
{"learn":[0.6054971533],"iteration":144,"passed_time":0.451855273,"remaining_time":2.664387989},
{"learn":[0.6039822717],"iteration":145,"passed_time":0.4560466353,"remaining_time":2.667560456},
{"learn":[0.6024946917],"iteration":146,"passed_time":0.4590542511,"remaining_time":2.663763784},
{"learn":[0.6010347355],"iteration":147,"passed_time":0.4616604837,"remaining_time":2.657667109},
{"learn":[0.5995852103],"iteration":148,"passed_time":0.463878894,"remaining_time":2.649402274},
{"learn":[0.598042149],"iteration":149,"passed_time":0.4660321489,"remaining_time":2.640848844},
{"learn":[0.5965763694],"iteration":150,"passed_time":0.468186701,"remaining_time":2.632387478},
{"learn":[0.5951904348],"iteration":151,"passed_time":0.4705050907,"remaining_time":2.624923137},
{"learn":[0.5937702342],"iteration":152,"passed_time":0.4727474691,"remaining_time":2.61710527},
{"learn":[0.5922940274],"iteration":153,"passed_time":0.4759102074,"remaining_time":2.614415815},
{"learn":[0.5909443785],"iteration":154,"passed_time":0.4781299025,"remaining_time":2.606579146},
{"learn":[0.5896101879],"iteration":155,"passed_time":0.4806753185,"remaining_time":2.600576723},
{"learn":[0.5882700973],"iteration":156,"passed_time":0.4830569313,"remaining_time":2.59373881},
{"learn":[0.5868538682],"iteration":157,"passed_time":0.4856578613,"remaining_time":2.588126071},
{"learn":[0.5855710844],"iteration":158,"passed_time":0.488418102,"remaining_time":2.58339386},
{"learn":[0.5841712927],"iteration":159,"passed_time":0.4907900606,"remaining_time":2.576647818},
{"learn":[0.5828394356],"iteration":160,"passed_time":0.4931791412,"remaining_time":2.570045338},
{"learn":[0.5814822357],"iteration":161,"passed_time":0.4960822694,"remaining_time":2.566153961},
{"learn":[0.5801076094],"iteration":162,"passed_time":0.4986812285,"remaining_time":2.560712811},
{"learn":[0.578794176],"iteration":163,"passed_time":0.5007460725,"remaining_time":2.552583638},
{"learn":[0.5774758852],"iteration":164,"passed_time":0.5032682883,"remaining_time":2.54684255},
{"learn":[0.5761653095],"iteration":165,"passed_time":0.505460306,"remaining_time":2.539481297},
{"learn":[0.574868134],"iteration":166,"passed_time":0.5076224516,"remaining_time":2.532032947},
{"learn":[0.5736649902],"iteration":167,"passed_time":0.5097844357,"remaining_time":2.524646729},
{"learn":[0.5723804367],"iteration":168,"passed_time":0.5122422095,"remaining_time":2.518776782},
{"learn":[0.5711201605],"iteration":169,"passed_time":0.5164295898,"remaining_time":2.521391527},
{"learn":[0.5698316121],"iteration":170,"passed_time":0.5190847788,"remaining_time":2.516498723},
{"learn":[0.5685525376],"iteration":171,"passed_time":0.521882605,"remaining_time":2.512318587},
{"learn":[0.5675157678],"iteration":172,"passed_time":0.5235036761,"remaining_time":2.502529134},
{"learn":[0.5662399354],"iteration":173,"passed_time":0.5258534621,"remaining_time":2.496292872},
{"learn":[0.5650925365],"iteration":174,"passed_time":0.5280765793,"remaining_time":2.489503874},
{"learn":[0.5638601274],"iteration":175,"passed_time":0.5302305174,"remaining_time":2.482442877},
{"learn":[0.5627582545],"iteration":176,"passed_time":0.5323707701,"remaining_time":2.475373694},
{"learn":[0.5616546967],"iteration":177,"passed_time":0.53545608,"remaining_time":2.472724145},
{"learn":[0.5604872828],"iteration":178,"passed_time":0.5385179889,"remaining_time":2.469962396},
{"learn":[0.5592505661],"iteration":179,"passed_time":0.5411213047,"remaining_time":2.465108166},
{"learn":[0.558116322],"iteration":180,"passed_time":0.543621219,"remaining_time":2.45981093},
{"learn":[0.5569786507],"iteration":181,"passed_time":0.5462618093,"remaining_time":2.455176703},
{"learn":[0.555745995],"iteration":182,"passed_time":0.5488658186,"remaining_time":2.45040095},
{"learn":[0.5546017603],"iteration":183,"passed_time":0.5515952198,"remaining_time":2.446204888},
{"learn":[0.5535148552],"iteration":184,"passed_time":0.5552753254,"remaining_time":2.44621292},
{"learn":[0.5523949938],"iteration":185,"passed_time":0.5580630448,"remaining_time":2.442275906},
{"learn":[0.5512500518],"iteration":186,"passed_time":0.5602189748,"remaining_time":2.43560442},
{"learn":[0.5501097659],"iteration":187,"passed_time":0.5623671591,"remaining_time":2.428947517},
{"learn":[0.5491616049],"iteration":188,"passed_time":0.5643526887,"remaining_time":2.421640373},
{"learn":[0.5479898099],"iteration":189,"passed_time":0.5668055046,"remaining_time":2.416381362},
{"learn":[0.5468663367],"iteration":190,"passed_time":0.5688979603,"remaining_time":2.409625392},
{"learn":[0.5458178615],"iteration":191,"passed_time":0.5708966389,"remaining_time":2.402523355},
{"learn":[0.5447005303],"iteration":192,"passed_time":0.573040161,"remaining_time":2.396079844},
{"learn":[0.5436389885],"iteration":193,"passed_time":0.5765199049,"remaining_time":2.395232182},
{"learn":[0.5425355813],"iteration":194,"passed_time":0.5795345869,"remaining_time":2.392437654},
{"learn":[0.5414532008],"iteration":195,"passed_time":0.5820412551,"remaining_time":2.387556985},
{"learn":[0.5404844731],"iteration":196,"passed_time":0.5846877611,"remaining_time":2.383270417},
{"learn":[0.5394513526],"iteration":197,"passed_time":0.5875653852,"remaining_time":2.37993656},
{"learn":[0.5385098902],"iteration":198,"passed_time":0.5894026038,"remaining_time":2.372419526},
{"learn":[0.5374395878],"iteration":199,"passed_time":0.5916077597,"remaining_time":2.366431039},
{"learn":[0.5363966705],"iteration":200,"passed_time":0.5944013745,"remaining_time":2.362819394},
{"learn":[0.5353824128],"iteration":201,"passed_time":0.5971116195,"remaining_time":2.358886497},
{"learn":[0.5344079383],"iteration":202,"passed_time":0.5996130522,"remaining_time":2.354145826},
{"learn":[0.5333695417],"iteration":203,"passed_time":0.6018155844,"remaining_time":2.34826081},
{"learn":[0.5323750949],"iteration":204,"passed_time":0.6042387396,"remaining_time":2.343267307},
{"learn":[0.5313992426],"iteration":205,"passed_time":0.6065039835,"remaining_time":2.337690111},
{"learn":[0.5304454941],"iteration":206,"passed_time":0.608722316,"remaining_time":2.331965201},
{"learn":[0.5296140506],"iteration":207,"passed_time":0.6111082439,"remaining_time":2.326912159},
{"learn":[0.5286712684],"iteration":208,"passed_time":0.6135572058,"remaining_time":2.322123205},
{"learn":[0.5277467682],"iteration":209,"passed_time":0.6166642476,"remaining_time":2.319832169},
{"learn":[0.5266675916],"iteration":210,"passed_time":0.6195566106,"remaining_time":2.316730643},
{"learn":[0.5257420991],"iteration":211,"passed_time":0.6220072087,"remaining_time":2.311989059},
{"learn":[0.5247407595],"iteration":212,"passed_time":0.6241057747,"remaining_time":2.305968285},
{"learn":[0.5236692579],"iteration":213,"passed_time":0.6261776343,"remaining_time":2.299886078},
{"learn":[0.5227090202],"iteration":214,"passed_time":0.628150221,"remaining_time":2.293478714},
{"learn":[0.521796115],"iteration":215,"passed_time":0.6303956548,"remaining_time":2.288102747},
{"learn":[0.5208826491],"iteration":216,"passed_time":0.6325064729,"remaining_time":2.2822699},
{"learn":[0.5199005489],"iteration":217,"passed_time":0.6349920385,"remaining_time":2.277815478},
{"learn":[0.5190244396],"iteration":218,"passed_time":0.6373994323,"remaining_time":2.273100259},
{"learn":[0.5180914359],"iteration":219,"passed_time":0.6395314303,"remaining_time":2.267429616},
{"learn":[0.5170580867],"iteration":220,"passed_time":0.641925503,"remaining_time":2.262714782},
{"learn":[0.5161377459],"iteration":221,"passed_time":0.6444172997,"remaining_time":2.25836333},
{"learn":[0.5153930429],"iteration":222,"passed_time":0.6470755815,"remaining_time":2.254608641},
{"learn":[0.5145060521],"iteration":223,"passed_time":0.6498571707,"remaining_time":2.251290913},
{"learn":[0.5136323246],"iteration":224,"passed_time":0.6521472552,"remaining_time":2.24628499},
{"learn":[0.5127254852],"iteration":225,"passed_time":0.6545798597,"remaining_time":2.241791201},
{"learn":[0.5118339043],"iteration":226,"passed_time":0.6569657331,"remaining_time":2.237156439},
{"learn":[0.5109512535],"iteration":227,"passed_time":0.6591835886,"remaining_time":2.231972502},
{"learn":[0.510077608],"iteration":228,"passed_time":0.6612905302,"remaining_time":2.226441043},
{"learn":[0.5092810205],"iteration":229,"passed_time":0.6635052832,"remaining_time":2.221300296},
{"learn":[0.5084568501],"iteration":230,"passed_time":0.6653692883,"remaining_time":2.215017241},
{"learn":[0.507685795],"iteration":231,"passed_time":0.6673420158,"remaining_time":2.20913219},
{"learn":[0.5068113326],"iteration":232,"passed_time":0.6695920332,"remaining_time":2.204193517},
{"learn":[0.5060340895],"iteration":233,"passed_time":0.6714937326,"remaining_time":2.198137603},
{"learn":[0.505199843],"iteration":234,"passed_time":0.6742370152,"remaining_time":2.194856667},
{"learn":[0.5043317668],"iteration":235,"passed_time":0.676946817,"remaining_time":2.191471899},
{"learn":[0.5036046869],"iteration":236,"passed_time":0.6788806976,"remaining_time":2.18559482},
{"learn":[0.5027401105],"iteration":237,"passed_time":0.6814523501,"remaining_time":2.181792818},
{"learn":[0.5019295827],"iteration":238,"passed_time":0.6838383527,"remaining_time":2.177409985},
{"learn":[0.501176604],"iteration":239,"passed_time":0.685911935,"remaining_time":2.172054461},
{"learn":[0.5003683826],"iteration":240,"passed_time":0.6878842502,"remaining_time":2.166407245},
{"learn":[0.4995609727],"iteration":241,"passed_time":0.6898020702,"remaining_time":2.160619707},
{"learn":[0.4987654991],"iteration":242,"passed_time":0.6917334923,"remaining_time":2.154906394},
{"learn":[0.4980660158],"iteration":243,"passed_time":0.6936950114,"remaining_time":2.14931733},
{"learn":[0.4973928012],"iteration":244,"passed_time":0.6968827974,"remaining_time":2.147536784},
{"learn":[0.4966322454],"iteration":245,"passed_time":0.6994949009,"remaining_time":2.143980306},
{"learn":[0.4958383176],"iteration":246,"passed_time":0.7020635316,"remaining_time":2.140298944},
{"learn":[0.4950868561],"iteration":247,"passed_time":0.7046863366,"remaining_time":2.136790827},
{"learn":[0.4943767464],"iteration":248,"passed_time":0.7073751308,"remaining_time":2.133488848},
{"learn":[0.4936561647],"iteration":249,"passed_time":0.7098715005,"remaining_time":2.129614501},
{"learn":[0.492926753],"iteration":250,"passed_time":0.7125941281,"remaining_time":2.126426303},
{"learn":[0.4921339386],"iteration":251,"passed_time":0.7164088455,"remaining_time":2.126483399},
{"learn":[0.491458379],"iteration":252,"passed_time":0.7179656097,"remaining_time":2.119843124},
{"learn":[0.4908277805],"iteration":253,"passed_time":0.7201271037,"remaining_time":2.115018974},
{"learn":[0.4903150554],"iteration":254,"passed_time":0.7215281535,"remaining_time":2.107994017},
{"learn":[0.4895712959],"iteration":255,"passed_time":0.7235692222,"remaining_time":2.102873052},
{"learn":[0.4887517501],"iteration":256,"passed_time":0.7257224075,"remaining_time":2.09810019},
{"learn":[0.4881029069],"iteration":257,"passed_time":0.7279002088,"remaining_time":2.09341843},
{"learn":[0.4873658603],"iteration":258,"passed_time":0.7300164846,"remaining_time":2.088579981},
{"learn":[0.4866247834],"iteration":259,"passed_time":0.7322735734,"remaining_time":2.084163247},
{"learn":[0.4858843779],"iteration":260,"passed_time":0.7351344622,"remaining_time":2.081472673},
{"learn":[0.4852654774],"iteration":261,"passed_time":0.7377147765,"remaining_time":2.077990477},
{"learn":[0.4845776612],"iteration":262,"passed_time":0.7401991571,"remaining_time":2.074246307},
{"learn":[0.4838912547],"iteration":263,"passed_time":0.7426112837,"remaining_time":2.070310245},
{"learn":[0.4832763951],"iteration":264,"passed_time":0.7455173614,"remaining_time":2.067755701},
{"learn":[0.4829610239],"iteration":265,"passed_time":0.7470590086,"remaining_time":2.061433505},
{"learn":[0.4823741379],"iteration":266,"passed_time":0.7491521255,"remaining_time":2.056661079},
{"learn":[0.4817509905],"iteration":267,"passed_time":0.7512132032,"remaining_time":2.051821137},
{"learn":[0.4810413889],"iteration":268,"passed_time":0.754010001,"remaining_time":2.049001155},
{"learn":[0.4803854126],"iteration":269,"passed_time":0.7568794417,"remaining_time":2.04637775},
{"learn":[0.4798240486],"iteration":270,"passed_time":0.7593513091,"remaining_time":2.042683042},
{"learn":[0.479517593],"iteration":271,"passed_time":0.7609055497,"remaining_time":2.036541324},
{"learn":[0.4788587765],"iteration":272,"passed_time":0.7636632875,"remaining_time":2.033638132},
{"learn":[0.4782326739],"iteration":273,"passed_time":0.7662419584,"remaining_time":2.030261539},
{"learn":[0.4774817621],"iteration":274,"passed_time":0.7690500555,"remaining_time":2.027495601},
{"learn":[0.47676155],"iteration":275,"passed_time":0.7718397617,"remaining_time":2.024681114},
{"learn":[0.4762070332],"iteration":276,"passed_time":0.7758749804,"remaining_time":2.025117729},
{"learn":[0.4756679101],"iteration":277,"passed_time":0.7789783666,"remaining_time":2.023102089},
{"learn":[0.4749112618],"iteration":278,"passed_time":0.7816391796,"remaining_time":2.019934941},
{"learn":[0.4743934713],"iteration":279,"passed_time":0.7842384983,"remaining_time":2.016613281},
{"learn":[0.4736330487],"iteration":280,"passed_time":0.786452014,"remaining_time":2.012309602},
{"learn":[0.4729506423],"iteration":281,"passed_time":0.7885542424,"remaining_time":2.007737397},
{"learn":[0.4722678843],"iteration":282,"passed_time":0.7910863524,"remaining_time":2.004271783},
{"learn":[0.4716961751],"iteration":283,"passed_time":0.7933263392,"remaining_time":2.000076264},
{"learn":[0.4712610653],"iteration":284,"passed_time":0.7953557842,"remaining_time":1.995366266},
{"learn":[0.4705904142],"iteration":285,"passed_time":0.797841626,"remaining_time":1.991814409},
{"learn":[0.4700248024],"iteration":286,"passed_time":0.8000598817,"remaining_time":1.987605211},
{"learn":[0.4695007159],"iteration":287,"passed_time":0.8022855025,"remaining_time":1.983428048},
{"learn":[0.4690642747],"iteration":288,"passed_time":0.8038955967,"remaining_time":1.977750067},
{"learn":[0.4686619605],"iteration":289,"passed_time":0.8052589749,"remaining_time":1.971496111},
{"learn":[0.4680660745],"iteration":290,"passed_time":0.8078217711,"remaining_time":1.968198061},
{"learn":[0.4674813262],"iteration":291,"passed_time":0.8102296157,"remaining_time":1.964529342},
{"learn":[0.467023862],"iteration":292,"passed_time":0.8122407799,"remaining_time":1.959912053},
{"learn":[0.4663732606],"iteration":293,"passed_time":0.8153200901,"remaining_time":1.957877495},
{"learn":[0.465646405],"iteration":294,"passed_time":0.817818158,"remaining_time":1.954446784},
{"learn":[0.4651940304],"iteration":295,"passed_time":0.8192254819,"remaining_time":1.948428173},
{"learn":[0.4645872678],"iteration":296,"passed_time":0.8212461757,"remaining_time":1.943892463},
{"learn":[0.4640359103],"iteration":297,"passed_time":0.8239352977,"remaining_time":1.940948252},
{"learn":[0.4637681896],"iteration":298,"passed_time":0.8257568321,"remaining_time":1.935971703},
{"learn":[0.4632047623],"iteration":299,"passed_time":0.828091957,"remaining_time":1.932214566},
{"learn":[0.4625563288],"iteration":300,"passed_time":0.8302592396,"remaining_time":1.928077105},
{"learn":[0.462103507],"iteration":301,"passed_time":0.8325642586,"remaining_time":1.924271035},
{"learn":[0.4615737394],"iteration":302,"passed_time":0.835409404,"remaining_time":1.921717342},
{"learn":[0.4610291467],"iteration":303,"passed_time":0.8382758228,"remaining_time":1.919210436},
{"learn":[0.4605472503],"iteration":304,"passed_time":0.8406575761,"remaining_time":1.915596772},
{"learn":[0.4601417797],"iteration":305,"passed_time":0.842604097,"remaining_time":1.911004063},
{"learn":[0.4595367854],"iteration":306,"passed_time":0.8451150864,"remaining_time":1.907702785},
{"learn":[0.4590446444],"iteration":307,"passed_time":0.8473351976,"remaining_time":1.903753106},
{"learn":[0.4586803698],"iteration":308,"passed_time":0.8489621596,"remaining_time":1.898488195},
{"learn":[0.4581225607],"iteration":309,"passed_time":0.8508709535,"remaining_time":1.893874058},
{"learn":[0.4575922633],"iteration":310,"passed_time":0.8527576309,"remaining_time":1.889228321},
{"learn":[0.4570867181],"iteration":311,"passed_time":0.8560147021,"remaining_time":1.887622164},
{"learn":[0.4565987048],"iteration":312,"passed_time":0.8584611253,"remaining_time":1.884226176},
{"learn":[0.4560725434],"iteration":313,"passed_time":0.861241232,"remaining_time":1.881565239},
{"learn":[0.455581791],"iteration":314,"passed_time":0.8633947186,"remaining_time":1.877540896},
{"learn":[0.4551554444],"iteration":315,"passed_time":0.8658955545,"remaining_time":1.874280251},
{"learn":[0.4546081815],"iteration":316,"passed_time":0.8683839619,"remaining_time":1.870997621},
{"learn":[0.4540208267],"iteration":317,"passed_time":0.8709002905,"remaining_time":1.867779868},
{"learn":[0.4534391554],"iteration":318,"passed_time":0.8736471127,"remaining_time":1.86505857},
{"learn":[0.4529221785],"iteration":319,"passed_time":0.8767937104,"remaining_time":1.863186635},
{"learn":[0.4525234631],"iteration":320,"passed_time":0.8787454699,"remaining_time":1.858779358},
{"learn":[0.4519940717],"iteration":321,"passed_time":0.8810477569,"remaining_time":1.855125401},
{"learn":[0.4515154808],"iteration":322,"passed_time":0.8832834528,"remaining_time":1.85134024},
{"learn":[0.4509655928],"iteration":323,"passed_time":0.8852046466,"remaining_time":1.84690846},
{"learn":[0.4505931595],"iteration":324,"passed_time":0.8873842551,"remaining_time":1.843028837},
{"learn":[0.4500534198],"iteration":325,"passed_time":0.8894428594,"remaining_time":1.83890947},
{"learn":[0.4498251441],"iteration":326,"passed_time":0.8904137314,"remaining_time":1.832564041},
{"learn":[0.449335524],"iteration":327,"passed_time":0.8926510882,"remaining_time":1.828846132},
{"learn":[0.4488701034],"iteration":328,"passed_time":0.8963976324,"remaining_time":1.828215232},
{"learn":[0.4483890416],"iteration":329,"passed_time":0.8991700096,"remaining_time":1.825587595},
{"learn":[0.4478806808],"iteration":330,"passed_time":0.9018658951,"remaining_time":1.822804483},
{"learn":[0.447287473],"iteration":331,"passed_time":0.9046861181,"remaining_time":1.820272069},
{"learn":[0.4468728699],"iteration":332,"passed_time":0.9070949366,"remaining_time":1.816913882},
{"learn":[0.446471142],"iteration":333,"passed_time":0.9094743061,"remaining_time":1.813502658},
{"learn":[0.4459478643],"iteration":334,"passed_time":0.9117553132,"remaining_time":1.809902338},
{"learn":[0.4455597788],"iteration":335,"passed_time":0.9142133821,"remaining_time":1.806659779},
{"learn":[0.4453086498],"iteration":336,"passed_time":0.9168680284,"remaining_time":1.803808614},
{"learn":[0.4448827378],"iteration":337,"passed_time":0.9189251743,"remaining_time":1.799788359},
{"learn":[0.4445057083],"iteration":338,"passed_time":0.9203350907,"remaining_time":1.794517684},
{"learn":[0.4441098218],"iteration":339,"passed_time":0.9223646973,"remaining_time":1.790472648},
{"learn":[0.4437231094],"iteration":340,"passed_time":0.9245482651,"remaining_time":1.78673697},
{"learn":[0.443290612],"iteration":341,"passed_time":0.9267449343,"remaining_time":1.783035575},
{"learn":[0.4427079019],"iteration":342,"passed_time":0.9288980486,"remaining_time":1.779259528},
{"learn":[0.4421685579],"iteration":343,"passed_time":0.9313467361,"remaining_time":1.776056567},
{"learn":[0.4418168095],"iteration":344,"passed_time":0.9336584646,"remaining_time":1.772597954},
{"learn":[0.4413155759],"iteration":345,"passed_time":0.9387425295,"remaining_time":1.774386168},
{"learn":[0.4407864788],"iteration":346,"passed_time":0.9417104698,"remaining_time":1.772152556},
{"learn":[0.4403345053],"iteration":347,"passed_time":0.9441959521,"remaining_time":1.769010807},
{"learn":[0.440007857],"iteration":348,"passed_time":0.9462984415,"remaining_time":1.765158411},
{"learn":[0.4395890066],"iteration":349,"passed_time":0.9484136732,"remaining_time":1.761339679},
{"learn":[0.4391480474],"iteration":350,"passed_time":0.9508645051,"remaining_time":1.758151179},
{"learn":[0.4388475417],"iteration":351,"passed_time":0.9531688498,"remaining_time":1.754697201},
{"learn":[0.4383884931],"iteration":352,"passed_time":0.9564698209,"remaining_time":1.753076414},
{"learn":[0.4379926373],"iteration":353,"passed_time":0.9588118131,"remaining_time":1.749696133},
{"learn":[0.4374075095],"iteration":354,"passed_time":0.9612038674,"remaining_time":1.74641266},
{"learn":[0.43701246],"iteration":355,"passed_time":0.9635231541,"remaining_time":1.74300256},
{"learn":[0.4366354852],"iteration":356,"passed_time":0.9659309598,"remaining_time":1.739758003},
{"learn":[0.4361706907],"iteration":357,"passed_time":0.9687735086,"remaining_time":1.737297744},
{"learn":[0.435845624],"iteration":358,"passed_time":0.9712127268,"remaining_time":1.734115203},
{"learn":[0.4354228494],"iteration":359,"passed_time":0.9734457917,"remaining_time":1.730570296},
{"learn":[0.4349618983],"iteration":360,"passed_time":0.9763153061,"remaining_time":1.728159226},
{"learn":[0.4346678656],"iteration":361,"passed_time":0.9792603134,"remaining_time":1.725878674},
{"learn":[0.4342272576],"iteration":362,"passed_time":0.9814826616,"remaining_time":1.722326324},
{"learn":[0.4337957509],"iteration":363,"passed_time":0.9839469951,"remaining_time":1.71920409},
{"learn":[0.433459994],"iteration":364,"passed_time":0.9859427472,"remaining_time":1.715270259},
{"learn":[0.4330581644],"iteration":365,"passed_time":0.9881171604,"remaining_time":1.711656502},
{"learn":[0.432622722],"iteration":366,"passed_time":0.9902197966,"remaining_time":1.707926788},
{"learn":[0.4323527109],"iteration":367,"passed_time":0.9923522278,"remaining_time":1.704257087},
{"learn":[0.4319369798],"iteration":368,"passed_time":0.9954819377,"remaining_time":1.702301091},
{"learn":[0.4313937677],"iteration":369,"passed_time":0.9984428134,"remaining_time":1.700051277},
{"learn":[0.4309739314],"iteration":370,"passed_time":1.000842075,"remaining_time":1.696845458},
{"learn":[0.4305516676],"iteration":371,"passed_time":1.003581185,"remaining_time":1.694217699},
{"learn":[0.430194337],"iteration":372,"passed_time":1.005821327,"remaining_time":1.690750595},
{"learn":[0.4298270144],"iteration":373,"passed_time":1.00819084,"remaining_time":1.687506594},
{"learn":[0.4294668018],"iteration":374,"passed_time":1.010181869,"remaining_time":1.683636448},
{"learn":[0.4291085],"iteration":375,"passed_time":1.012173579,"remaining_time":1.67977743},
{"learn":[0.4287821902],"iteration":376,"passed_time":1.014888587,"remaining_time":1.67712358},
{"learn":[0.4285089701],"iteration":377,"passed_time":1.01767466,"remaining_time":1.674586346},
{"learn":[0.4281141605],"iteration":378,"passed_time":1.021016267,"remaining_time":1.672958053},
{"learn":[0.4279434835],"iteration":379,"passed_time":1.022862297,"remaining_time":1.66888059},
{"learn":[0.4276757497],"iteration":380,"passed_time":1.026165097,"remaining_time":1.667181614},
{"learn":[0.4273455976],"iteration":381,"passed_time":1.029077199,"remaining_time":1.66484217},
{"learn":[0.4270607177],"iteration":382,"passed_time":1.032073026,"remaining_time":1.662634614},
{"learn":[0.4265632418],"iteration":383,"passed_time":1.036315676,"remaining_time":1.662423064},
{"learn":[0.4262295513],"iteration":384,"passed_time":1.039806472,"remaining_time":1.660989559},
{"learn":[0.4259553181],"iteration":385,"passed_time":1.042034059,"remaining_time":1.657536043},
{"learn":[0.4256193162],"iteration":386,"passed_time":1.044089476,"remaining_time":1.653816146},
{"learn":[0.4253042533],"iteration":387,"passed_time":1.046523267,"remaining_time":1.650701648},
{"learn":[0.4249959493],"iteration":388,"passed_time":1.04951832,"remaining_time":1.64847222},
{"learn":[0.4246429103],"iteration":389,"passed_time":1.052470568,"remaining_time":1.646171914},
{"learn":[0.4241756414],"iteration":390,"passed_time":1.055179216,"remaining_time":1.643488856},
{"learn":[0.423827436],"iteration":391,"passed_time":1.061949224,"remaining_time":1.647104919},
{"learn":[0.4234967638],"iteration":392,"passed_time":1.067308435,"remaining_time":1.648489109},
{"learn":[0.4232033718],"iteration":393,"passed_time":1.072735905,"remaining_time":1.649944056},
{"learn":[0.422749923],"iteration":394,"passed_time":1.079477625,"remaining_time":1.653377122},
{"learn":[0.4224302899],"iteration":395,"passed_time":1.086983656,"remaining_time":1.657924566},
{"learn":[0.4221050955],"iteration":396,"passed_time":1.09034031,"remaining_time":1.656108834},
{"learn":[0.4216159777],"iteration":397,"passed_time":1.093361072,"remaining_time":1.6537773},
{"learn":[0.4213480072],"iteration":398,"passed_time":1.098452472,"remaining_time":1.654561242},
{"learn":[0.4211909692],"iteration":399,"passed_time":1.101934597,"remaining_time":1.652901896},
{"learn":[0.4208423505],"iteration":400,"passed_time":1.106568439,"remaining_time":1.652953853},
{"learn":[0.420629386],"iteration":401,"passed_time":1.109176966,"remaining_time":1.649969715},
{"learn":[0.4203798532],"iteration":402,"passed_time":1.112248251,"remaining_time":1.647672967},
{"learn":[0.4200727733],"iteration":403,"passed_time":1.115322709,"remaining_time":1.645377065},
{"learn":[0.4197469854],"iteration":404,"passed_time":1.119104606,"remaining_time":1.644116643},
{"learn":[0.4193776431],"iteration":405,"passed_time":1.122819796,"remaining_time":1.642746204},
{"learn":[0.4191373802],"iteration":406,"passed_time":1.126638383,"remaining_time":1.641514892},
{"learn":[0.4189735088],"iteration":407,"passed_time":1.130890517,"remaining_time":1.640899966},
{"learn":[0.418486668],"iteration":408,"passed_time":1.13503915,"remaining_time":1.640117695},
{"learn":[0.4180402963],"iteration":409,"passed_time":1.139612671,"remaining_time":1.639930429},
{"learn":[0.417738812],"iteration":410,"passed_time":1.142855691,"remaining_time":1.63781509},
{"learn":[0.4174294881],"iteration":411,"passed_time":1.145758204,"remaining_time":1.63520831},
{"learn":[0.4170640479],"iteration":412,"passed_time":1.149130386,"remaining_time":1.633267644},
{"learn":[0.4167542501],"iteration":413,"passed_time":1.152493317,"remaining_time":1.631306965},
{"learn":[0.4164132646],"iteration":414,"passed_time":1.158268521,"remaining_time":1.632739963},
{"learn":[0.4160245731],"iteration":415,"passed_time":1.162272659,"remaining_time":1.631652002},
{"learn":[0.4157144991],"iteration":416,"passed_time":1.166085995,"remaining_time":1.630283298},
{"learn":[0.4153591867],"iteration":417,"passed_time":1.16948073,"remaining_time":1.628320059},
{"learn":[0.4151496488],"iteration":418,"passed_time":1.172769702,"remaining_time":1.626203334},
{"learn":[0.4146509816],"iteration":419,"passed_time":1.176577395,"remaining_time":1.624797355},
{"learn":[0.4143748751],"iteration":420,"passed_time":1.18093961,"remaining_time":1.624142599},
{"learn":[0.4141223724],"iteration":421,"passed_time":1.184517463,"remaining_time":1.622395957},
{"learn":[0.4139123972],"iteration":422,"passed_time":1.187710346,"remaining_time":1.620115531},
{"learn":[0.4136328992],"iteration":423,"passed_time":1.191262168,"remaining_time":1.618318416},
{"learn":[0.4134129699],"iteration":424,"passed_time":1.194541822,"remaining_time":1.616144818},
{"learn":[0.4131815804],"iteration":425,"passed_time":1.198563891,"remaining_time":1.61496637},
{"learn":[0.4129327569],"iteration":426,"passed_time":1.202738208,"remaining_time":1.613978907},
{"learn":[0.4126202707],"iteration":427,"passed_time":1.206404144,"remaining_time":1.612297127},
{"learn":[0.4123901493],"iteration":428,"passed_time":1.208996187,"remaining_time":1.609176743},
{"learn":[0.4122082139],"iteration":429,"passed_time":1.211963591,"remaining_time":1.606556387},
{"learn":[0.4119857508],"iteration":430,"passed_time":1.215072932,"remaining_time":1.604121805},
{"learn":[0.4118567984],"iteration":431,"passed_time":1.21736865,"remaining_time":1.600614336},
{"learn":[0.4116106343],"iteration":432,"passed_time":1.221005196,"remaining_time":1.598868236},
{"learn":[0.4112075527],"iteration":433,"passed_time":1.224526227,"remaining_time":1.596962776},
{"learn":[0.4108985749],"iteration":434,"passed_time":1.227873669,"remaining_time":1.594824421},
{"learn":[0.4106899505],"iteration":435,"passed_time":1.231038325,"remaining_time":1.592444071},
{"learn":[0.4103824295],"iteration":436,"passed_time":1.234086246,"remaining_time":1.589909741},
{"learn":[0.4099601995],"iteration":437,"passed_time":1.237807188,"remaining_time":1.58823662},
{"learn":[0.409622324],"iteration":438,"passed_time":1.24004512,"remaining_time":1.584659026},
{"learn":[0.4093849522],"iteration":439,"passed_time":1.242219686,"remaining_time":1.581006874},
{"learn":[0.4090885885],"iteration":440,"passed_time":1.244516042,"remaining_time":1.577515799},
{"learn":[0.4087907433],"iteration":441,"passed_time":1.247209463,"remaining_time":1.574531404},
{"learn":[0.4084811432],"iteration":442,"passed_time":1.249769463,"remaining_time":1.571380566},
{"learn":[0.4082631203],"iteration":443,"passed_time":1.252371334,"remaining_time":1.568284824},
{"learn":[0.4079516697],"iteration":444,"passed_time":1.255075393,"remaining_time":1.565318749},
{"learn":[0.4077074938],"iteration":445,"passed_time":1.25992045,"remaining_time":1.565013294},
{"learn":[0.4074753516],"iteration":446,"passed_time":1.262381858,"remaining_time":1.56173863},
{"learn":[0.4071448658],"iteration":447,"passed_time":1.264985241,"remaining_time":1.558642529},
{"learn":[0.4067509827],"iteration":448,"passed_time":1.267287121,"remaining_time":1.555178628},
{"learn":[0.4064572339],"iteration":449,"passed_time":1.269272614,"remaining_time":1.551333194},
{"learn":[0.4061661152],"iteration":450,"passed_time":1.271317322,"remaining_time":1.547568092},
{"learn":[0.405932387],"iteration":451,"passed_time":1.273699741,"remaining_time":1.54422004},
{"learn":[0.405663946],"iteration":452,"passed_time":1.276492476,"remaining_time":1.54137171},
{"learn":[0.4053744523],"iteration":453,"passed_time":1.279143917,"remaining_time":1.538353697},
{"learn":[0.4050268639],"iteration":454,"passed_time":1.281153349,"remaining_time":1.534568297},
{"learn":[0.4048767961],"iteration":455,"passed_time":1.283583951,"remaining_time":1.531293135},
{"learn":[0.4046106286],"iteration":456,"passed_time":1.285947363,"remaining_time":1.527941834},
{"learn":[0.404431946],"iteration":457,"passed_time":1.288804044,"remaining_time":1.525178585},
{"learn":[0.4041253498],"iteration":458,"passed_time":1.291669305,"remaining_time":1.522425041},
{"learn":[0.4037283264],"iteration":459,"passed_time":1.293978726,"remaining_time":1.519018505},
{"learn":[0.4034309232],"iteration":460,"passed_time":1.29750733,"remaining_time":1.517042193},
{"learn":[0.4033193365],"iteration":461,"passed_time":1.299108434,"remaining_time":1.512814583},
{"learn":[0.4030923742],"iteration":462,"passed_time":1.301475415,"remaining_time":1.509486605},
{"learn":[0.4029771994],"iteration":463,"passed_time":1.302944216,"remaining_time":1.505125215},
{"learn":[0.4025627122],"iteration":464,"passed_time":1.305146538,"remaining_time":1.501620211},
{"learn":[0.4023482959],"iteration":465,"passed_time":1.307391399,"remaining_time":1.498169543},
{"learn":[0.4021253706],"iteration":466,"passed_time":1.31022676,"remaining_time":1.495397994},
{"learn":[0.4017767354],"iteration":467,"passed_time":1.312759741,"remaining_time":1.492282441},
{"learn":[0.4015688737],"iteration":468,"passed_time":1.315539792,"remaining_time":1.489449104},
{"learn":[0.4013423384],"iteration":469,"passed_time":1.319084594,"remaining_time":1.487478371},
{"learn":[0.4009960285],"iteration":470,"passed_time":1.322405128,"remaining_time":1.485249072},
{"learn":[0.4008727672],"iteration":471,"passed_time":1.325415279,"remaining_time":1.48266794},
{"learn":[0.4005635917],"iteration":472,"passed_time":1.327703824,"remaining_time":1.479281005},
{"learn":[0.4003516716],"iteration":473,"passed_time":1.329740236,"remaining_time":1.475618912},
{"learn":[0.4001269272],"iteration":474,"passed_time":1.332208117,"remaining_time":1.47244055},
{"learn":[0.3998955921],"iteration":475,"passed_time":1.334273275,"remaining_time":1.46882184},
{"learn":[0.3996212551],"iteration":476,"passed_time":1.337313542,"remaining_time":1.466278789},
{"learn":[0.3993579371],"iteration":477,"passed_time":1.339966952,"remaining_time":1.46331119},
{"learn":[0.3991454887],"iteration":478,"passed_time":1.342820397,"remaining_time":1.460562478},
{"learn":[0.3990091373],"iteration":479,"passed_time":1.34553398,"remaining_time":1.457661811},
{"learn":[0.3988093427],"iteration":480,"passed_time":1.347547871,"remaining_time":1.454006954},
{"learn":[0.3985800357],"iteration":481,"passed_time":1.35000509,"remaining_time":1.450835346},
{"learn":[0.3983595435],"iteration":482,"passed_time":1.353010463,"remaining_time":1.448253435},
{"learn":[0.3981249526],"iteration":483,"passed_time":1.356997495,"remaining_time":1.446716337},
{"learn":[0.3979417123],"iteration":484,"passed_time":1.359382434,"remaining_time":1.443467945},
{"learn":[0.3975243304],"iteration":485,"passed_time":1.361732636,"remaining_time":1.440186368},
{"learn":[0.3973892607],"iteration":486,"passed_time":1.364263899,"remaining_time":1.437099344},
{"learn":[0.3972271892],"iteration":487,"passed_time":1.366317726,"remaining_time":1.433513679},
{"learn":[0.3970576747],"iteration":488,"passed_time":1.368348176,"remaining_time":1.429909853},
{"learn":[0.3968759317],"iteration":489,"passed_time":1.370486835,"remaining_time":1.426425074},
{"learn":[0.3964320977],"iteration":490,"passed_time":1.3725174,"remaining_time":1.42283372},
{"learn":[0.3961626482],"iteration":491,"passed_time":1.375679355,"remaining_time":1.420416895},
{"learn":[0.39596344],"iteration":492,"passed_time":1.378539741,"remaining_time":1.417686914},
{"learn":[0.3957399461],"iteration":493,"passed_time":1.380955978,"remaining_time":1.414501467},
{"learn":[0.3955689465],"iteration":494,"passed_time":1.38346668,"remaining_time":1.411415502},
{"learn":[0.3954668369],"iteration":495,"passed_time":1.386331802,"remaining_time":1.408691992},
{"learn":[0.3951136165],"iteration":496,"passed_time":1.388902545,"remaining_time":1.40566998},
{"learn":[0.3949255565],"iteration":497,"passed_time":1.390979165,"remaining_time":1.402151689},
{"learn":[0.3946348478],"iteration":498,"passed_time":1.393118551,"remaining_time":1.398702193},
{"learn":[0.3942992251],"iteration":499,"passed_time":1.396179362,"remaining_time":1.396179362},
{"learn":[0.3941470154],"iteration":500,"passed_time":1.399186545,"remaining_time":1.39360097},
{"learn":[0.3939834637],"iteration":501,"passed_time":1.401610808,"remaining_time":1.390442594},
{"learn":[0.3937913989],"iteration":502,"passed_time":1.404011824,"remaining_time":1.387264168},
{"learn":[0.3935986321],"iteration":503,"passed_time":1.407203146,"remaining_time":1.384866588},
{"learn":[0.3934129612],"iteration":504,"passed_time":1.409949139,"remaining_time":1.382029354},
{"learn":[0.3932368355],"iteration":505,"passed_time":1.411946982,"remaining_time":1.378462073},
{"learn":[0.3929818986],"iteration":506,"passed_time":1.414843027,"remaining_time":1.375774383},
{"learn":[0.392854695],"iteration":507,"passed_time":1.419502711,"remaining_time":1.374793965},
{"learn":[0.3927311055],"iteration":508,"passed_time":1.422218838,"remaining_time":1.371924262},
{"learn":[0.3926002725],"iteration":509,"passed_time":1.423919172,"remaining_time":1.368079205},
{"learn":[0.3925119032],"iteration":510,"passed_time":1.424990943,"remaining_time":1.36364104},
{"learn":[0.3922036395],"iteration":511,"passed_time":1.427200498,"remaining_time":1.360300474},
{"learn":[0.3919811644],"iteration":512,"passed_time":1.42970042,"remaining_time":1.35723997},
{"learn":[0.3918184164],"iteration":513,"passed_time":1.431688968,"remaining_time":1.35369813},
{"learn":[0.3916971687],"iteration":514,"passed_time":1.433933047,"remaining_time":1.350402967},
{"learn":[0.391559886],"iteration":515,"passed_time":1.436459232,"remaining_time":1.347376489},
{"learn":[0.3914011862],"iteration":516,"passed_time":1.439281871,"remaining_time":1.344628904},
{"learn":[0.3912174024],"iteration":517,"passed_time":1.441998192,"remaining_time":1.341782102},
{"learn":[0.390892083],"iteration":518,"passed_time":1.444861135,"remaining_time":1.339071688},
{"learn":[0.3905541858],"iteration":519,"passed_time":1.447488036,"remaining_time":1.336142802},
{"learn":[0.3904131794],"iteration":520,"passed_time":1.450494831,"remaining_time":1.333564346},
{"learn":[0.3901867362],"iteration":521,"passed_time":1.453034228,"remaining_time":1.330556247},
{"learn":[0.3898396772],"iteration":522,"passed_time":1.45572659,"remaining_time":1.327689452},
{"learn":[0.3896179137],"iteration":523,"passed_time":1.458063532,"remaining_time":1.32450046},
{"learn":[0.3894712484],"iteration":524,"passed_time":1.460537946,"remaining_time":1.321439094},
{"learn":[0.3893368623],"iteration":525,"passed_time":1.462662056,"remaining_time":1.318064286},
{"learn":[0.3891971667],"iteration":526,"passed_time":1.464527852,"remaining_time":1.314462379},
{"learn":[0.3891127803],"iteration":527,"passed_time":1.46648714,"remaining_time":1.310950626},
{"learn":[0.3889508659],"iteration":528,"passed_time":1.468531963,"remaining_time":1.307520897},
{"learn":[0.3887998123],"iteration":529,"passed_time":1.470906729,"remaining_time":1.304388986},
{"learn":[0.3886896844],"iteration":530,"passed_time":1.473728039,"remaining_time":1.301654332},
{"learn":[0.3885235639],"iteration":531,"passed_time":1.477765511,"remaining_time":1.299989209},
{"learn":[0.3882868905],"iteration":532,"passed_time":1.480209963,"remaining_time":1.296919424},
{"learn":[0.3880650692],"iteration":533,"passed_time":1.483392334,"remaining_time":1.294495932},
{"learn":[0.3878823204],"iteration":534,"passed_time":1.486222887,"remaining_time":1.291763817},
{"learn":[0.3877139621],"iteration":535,"passed_time":1.488461343,"remaining_time":1.288518775},
{"learn":[0.3875826745],"iteration":536,"passed_time":1.49011845,"remaining_time":1.284776243},
{"learn":[0.3874046794],"iteration":537,"passed_time":1.492373814,"remaining_time":1.281555209},
{"learn":[0.3871767615],"iteration":538,"passed_time":1.49486458,"remaining_time":1.278539093},
{"learn":[0.3870914436],"iteration":539,"passed_time":1.497356412,"remaining_time":1.275525833},
{"learn":[0.3870165215],"iteration":540,"passed_time":1.4985372,"remaining_time":1.271402171},
{"learn":[0.3869449394],"iteration":541,"passed_time":1.499715647,"remaining_time":1.267287391},
{"learn":[0.3866533149],"iteration":542,"passed_time":1.50256312,"remaining_time":1.264588114},
{"learn":[0.3864940653],"iteration":543,"passed_time":1.505401082,"remaining_time":1.261880318},
{"learn":[0.3863010044],"iteration":544,"passed_time":1.507920778,"remaining_time":1.258906337},
{"learn":[0.386025305],"iteration":545,"passed_time":1.510530461,"remaining_time":1.256008845},
{"learn":[0.3858000783],"iteration":546,"passed_time":1.512988072,"remaining_time":1.252986465},
{"learn":[0.3856627148],"iteration":547,"passed_time":1.51735204,"remaining_time":1.251538544},
{"learn":[0.3855468412],"iteration":548,"passed_time":1.51954738,"remaining_time":1.248298486},
{"learn":[0.3854248249],"iteration":549,"passed_time":1.521455402,"remaining_time":1.244827147},
{"learn":[0.3851293947],"iteration":550,"passed_time":1.523597045,"remaining_time":1.241551857},
{"learn":[0.3850169521],"iteration":551,"passed_time":1.52587497,"remaining_time":1.23839128},
{"learn":[0.384845599],"iteration":552,"passed_time":1.527923772,"remaining_time":1.235048691},
{"learn":[0.3847012538],"iteration":553,"passed_time":1.52985815,"remaining_time":1.231618655},
{"learn":[0.3845410891],"iteration":554,"passed_time":1.531633833,"remaining_time":1.228066767},
{"learn":[0.3842802566],"iteration":555,"passed_time":1.534240164,"remaining_time":1.225184591},
{"learn":[0.3840689369],"iteration":556,"passed_time":1.537553347,"remaining_time":1.222865588},
{"learn":[0.3838666043],"iteration":557,"passed_time":1.540427787,"remaining_time":1.220195487},
{"learn":[0.3836926924],"iteration":558,"passed_time":1.543201109,"remaining_time":1.217444882},
{"learn":[0.3835412073],"iteration":559,"passed_time":1.546104268,"remaining_time":1.214796211},
{"learn":[0.383310934],"iteration":560,"passed_time":1.548904571,"remaining_time":1.212066144},
{"learn":[0.383067258],"iteration":561,"passed_time":1.550920143,"remaining_time":1.20872424},
{"learn":[0.3829457382],"iteration":562,"passed_time":1.553249002,"remaining_time":1.20563022},
{"learn":[0.3826415237],"iteration":563,"passed_time":1.556155435,"remaining_time":1.202985408},
{"learn":[0.3823151638],"iteration":564,"passed_time":1.559010206,"remaining_time":1.200299893},
{"learn":[0.3820949614],"iteration":565,"passed_time":1.561000332,"remaining_time":1.196950785},
{"learn":[0.3819512931],"iteration":566,"passed_time":1.562960364,"remaining_time":1.193583488},
{"learn":[0.381792578],"iteration":567,"passed_time":1.565272601,"remaining_time":1.19048902},
{"learn":[0.3815569876],"iteration":568,"passed_time":1.567476239,"remaining_time":1.187315042},
{"learn":[0.3813850372],"iteration":569,"passed_time":1.570231864,"remaining_time":1.18456088},
{"learn":[0.3812619506],"iteration":570,"passed_time":1.572715365,"remaining_time":1.181602262},
{"learn":[0.3811505101],"iteration":571,"passed_time":1.576096103,"remaining_time":1.179316664},
{"learn":[0.38079549],"iteration":572,"passed_time":1.579575601,"remaining_time":1.17710084},
{"learn":[0.380656192],"iteration":573,"passed_time":1.582284274,"remaining_time":1.174308538},
{"learn":[0.3805492269],"iteration":574,"passed_time":1.585258105,"remaining_time":1.171712512},
{"learn":[0.3804575205],"iteration":575,"passed_time":1.587376431,"remaining_time":1.168485428},
{"learn":[0.3802788126],"iteration":576,"passed_time":1.58985276,"remaining_time":1.165524641},
{"learn":[0.3800965268],"iteration":577,"passed_time":1.591204462,"remaining_time":1.161744434},
{"learn":[0.379986151],"iteration":578,"passed_time":1.593255746,"remaining_time":1.158481294},
{"learn":[0.3797941512],"iteration":579,"passed_time":1.596519528,"remaining_time":1.156100348},
{"learn":[0.3795058747],"iteration":580,"passed_time":1.59895753,"remaining_time":1.153120835},
{"learn":[0.3792871868],"iteration":581,"passed_time":1.601635663,"remaining_time":1.150315648},
{"learn":[0.3791060152],"iteration":582,"passed_time":1.604041348,"remaining_time":1.147316024},
{"learn":[0.3790263966],"iteration":583,"passed_time":1.606239401,"remaining_time":1.144170532},
{"learn":[0.3788966079],"iteration":584,"passed_time":1.608425979,"remaining_time":1.141020139},
{"learn":[0.3788086533],"iteration":585,"passed_time":1.610825321,"remaining_time":1.13802335},
{"learn":[0.3786059778],"iteration":586,"passed_time":1.613246949,"remaining_time":1.135044276},
{"learn":[0.3784759155],"iteration":587,"passed_time":1.616013856,"remaining_time":1.132309028},
{"learn":[0.3783282385],"iteration":588,"passed_time":1.618848285,"remaining_time":1.12962079},
{"learn":[0.3782038204],"iteration":589,"passed_time":1.621364134,"remaining_time":1.12671067},
{"learn":[0.3779685496],"iteration":590,"passed_time":1.623862829,"remaining_time":1.123790012},
{"learn":[0.377671447],"iteration":591,"passed_time":1.626234176,"remaining_time":1.120783014},
{"learn":[0.3774766304],"iteration":592,"passed_time":1.628640379,"remaining_time":1.117802081},
{"learn":[0.3772368787],"iteration":593,"passed_time":1.630930569,"remaining_time":1.114743789},
{"learn":[0.3770323011],"iteration":594,"passed_time":1.633976044,"remaining_time":1.112202181},
{"learn":[0.3768836356],"iteration":595,"passed_time":1.636957673,"remaining_time":1.109615604},
{"learn":[0.3767965993],"iteration":596,"passed_time":1.639279122,"remaining_time":1.106582054},
{"learn":[0.3767212166],"iteration":597,"passed_time":1.641646008,"remaining_time":1.10358143},
{"learn":[0.3765824639],"iteration":598,"passed_time":1.644315277,"remaining_time":1.100785352},
{"learn":[0.3763549029],"iteration":599,"passed_time":1.646607632,"remaining_time":1.097738421},
{"learn":[0.3762481491],"iteration":600,"passed_time":1.648566327,"remaining_time":1.094472486},
{"learn":[0.3761120921],"iteration":601,"passed_time":1.650568723,"remaining_time":1.091239787},
{"learn":[0.3759932067],"iteration":602,"passed_time":1.652719309,"remaining_time":1.088108732},
{"learn":[0.3757400393],"iteration":603,"passed_time":1.655274337,"remaining_time":1.085246088},
{"learn":[0.3756305276],"iteration":604,"passed_time":1.658402917,"remaining_time":1.082758929},
{"learn":[0.3754136325],"iteration":605,"passed_time":1.661397928,"remaining_time":1.080182811},
{"learn":[0.3752385902],"iteration":606,"passed_time":1.663687237,"remaining_time":1.077148409},
{"learn":[0.3751603091],"iteration":607,"passed_time":1.666391641,"remaining_time":1.074384084},
{"learn":[0.3750782802],"iteration":608,"passed_time":1.669014221,"remaining_time":1.071567422},
{"learn":[0.3750340421],"iteration":609,"passed_time":1.670228649,"remaining_time":1.067851104},
{"learn":[0.3749229709],"iteration":610,"passed_time":1.67267299,"remaining_time":1.064926011},
{"learn":[0.3748093805],"iteration":611,"passed_time":1.676241019,"remaining_time":1.062714895},
{"learn":[0.3746756264],"iteration":612,"passed_time":1.678633983,"remaining_time":1.059757506},
{"learn":[0.3744537672],"iteration":613,"passed_time":1.680795851,"remaining_time":1.056656675},
{"learn":[0.3743582537],"iteration":614,"passed_time":1.682685853,"remaining_time":1.053388704},
{"learn":[0.3741106468],"iteration":615,"passed_time":1.684633383,"remaining_time":1.05016107},
{"learn":[0.3739434409],"iteration":616,"passed_time":1.686942489,"remaining_time":1.047162032},
{"learn":[0.3736783091],"iteration":617,"passed_time":1.689047913,"remaining_time":1.044039325},
{"learn":[0.3736043549],"iteration":618,"passed_time":1.690382668,"remaining_time":1.040445552},
{"learn":[0.373527692],"iteration":619,"passed_time":1.692377384,"remaining_time":1.037263558},
{"learn":[0.3733055426],"iteration":620,"passed_time":1.694655654,"remaining_time":1.034258443},
{"learn":[0.3731627076],"iteration":621,"passed_time":1.697949979,"remaining_time":1.031873138},
{"learn":[0.3730968955],"iteration":622,"passed_time":1.700338355,"remaining_time":1.028936693},
{"learn":[0.3729605728],"iteration":623,"passed_time":1.702845013,"remaining_time":1.026073277},
{"learn":[0.3727994709],"iteration":624,"passed_time":1.704821704,"remaining_time":1.022893022},
{"learn":[0.372580057],"iteration":625,"passed_time":1.707378561,"remaining_time":1.020063229},
{"learn":[0.3724047323],"iteration":626,"passed_time":1.710150192,"remaining_time":1.017362076},
{"learn":[0.3722827051],"iteration":627,"passed_time":1.712301311,"remaining_time":1.014293133},
{"learn":[0.3722096741],"iteration":628,"passed_time":1.714023065,"remaining_time":1.010973859},
{"learn":[0.3720535266],"iteration":629,"passed_time":1.716459986,"remaining_time":1.008079674},
{"learn":[0.3719756534],"iteration":630,"passed_time":1.718662232,"remaining_time":1.005049705},
{"learn":[0.3717730225],"iteration":631,"passed_time":1.721218043,"remaining_time":1.002228228},
{"learn":[0.371617113],"iteration":632,"passed_time":1.723169299,"remaining_time":0.9990570816},
{"learn":[0.3715442657],"iteration":633,"passed_time":1.725499402,"remaining_time":0.9961084876},
{"learn":[0.3713308868],"iteration":634,"passed_time":1.727880438,"remaining_time":0.9931911181},
{"learn":[0.3711822632],"iteration":635,"passed_time":1.730403363,"remaining_time":0.9903566418},
{"learn":[0.3710829852],"iteration":636,"passed_time":1.732815991,"remaining_time":0.9874602903},
{"learn":[0.3709538244],"iteration":637,"passed_time":1.736070914,"remaining_time":0.9850433711},
{"learn":[0.3708552339],"iteration":638,"passed_time":1.739112576,"remaining_time":0.9825033486},
{"learn":[0.3707287564],"iteration":639,"passed_time":1.741782977,"remaining_time":0.9797529247},
{"learn":[0.3705917894],"iteration":640,"passed_time":1.743769935,"remaining_time":0.976619979},
{"learn":[0.3703755917],"iteration":641,"passed_time":1.745864911,"remaining_time":0.973550838},
{"learn":[0.3702669725],"iteration":642,"passed_time":1.747961694,"remaining_time":0.9704857306},
{"learn":[0.3701889547],"iteration":643,"passed_time":1.750001324,"remaining_time":0.9673920363},
{"learn":[0.3700595856],"iteration":644,"passed_time":1.752425823,"remaining_time":0.9645134375},
{"learn":[0.3699457345],"iteration":645,"passed_time":1.755440993,"remaining_time":0.9619599248},
{"learn":[0.3697670147],"iteration":646,"passed_time":1.757788659,"remaining_time":0.9590407985},
{"learn":[0.3696679516],"iteration":647,"passed_time":1.759969907,"remaining_time":0.9560330361},
{"learn":[0.3695544858],"iteration":648,"passed_time":1.76259462,"remaining_time":0.9532676606},
{"learn":[0.3694650323],"iteration":649,"passed_time":1.765168009,"remaining_time":0.9504750817},
{"learn":[0.3691469807],"iteration":650,"passed_time":1.767660032,"remaining_time":0.9476395562},
{"learn":[0.3690295477],"iteration":651,"passed_time":1.770074113,"remaining_time":0.9447634836},
{"learn":[0.3688815425],"iteration":652,"passed_time":1.772110253,"remaining_time":0.9416879905},
{"learn":[0.3686612077],"iteration":653,"passed_time":1.774582196,"remaining_time":0.9388462384},
{"learn":[0.3684461824],"iteration":654,"passed_time":1.77710209,"remaining_time":0.9360308719},
{"learn":[0.3684112501],"iteration":655,"passed_time":1.778683234,"remaining_time":0.9327241351},
{"learn":[0.3682691104],"iteration":656,"passed_time":1.780595783,"remaining_time":0.9295956676},
{"learn":[0.368193014],"iteration":657,"passed_time":1.782167568,"remaining_time":0.9262937815},
{"learn":[0.3678464082],"iteration":658,"passed_time":1.784378019,"remaining_time":0.9233276246},
{"learn":[0.3676217946],"iteration":659,"passed_time":1.786294497,"remaining_time":0.9202123168},
{"learn":[0.367533023],"iteration":660,"passed_time":1.788364761,"remaining_time":0.9171795068},
{"learn":[0.367180993],"iteration":661,"passed_time":1.790798011,"remaining_time":0.9143349363},
{"learn":[0.3670849779],"iteration":662,"passed_time":1.793449613,"remaining_time":0.9116025938},
{"learn":[0.3669888814],"iteration":663,"passed_time":1.797527067,"remaining_time":0.9095920096},
{"learn":[0.366874633],"iteration":664,"passed_time":1.800121544,"remaining_time":0.9068281464},
{"learn":[0.3666268717],"iteration":665,"passed_time":1.802860045,"remaining_time":0.9041370194},
{"learn":[0.3665448432],"iteration":666,"passed_time":1.805635663,"remaining_time":0.9014642815},
{"learn":[0.3662623406],"iteration":667,"passed_time":1.807820057,"remaining_time":0.8984973934},
{"learn":[0.3662285187],"iteration":668,"passed_time":1.809778905,"remaining_time":0.8954212518},
{"learn":[0.3660159198],"iteration":669,"passed_time":1.811898088,"remaining_time":0.8924274164},
{"learn":[0.3658357656],"iteration":670,"passed_time":1.815806513,"remaining_time":0.8903134768},
{"learn":[0.3657858623],"iteration":671,"passed_time":1.817730632,"remaining_time":0.8872256655},
{"learn":[0.3656727998],"iteration":672,"passed_time":1.821029861,"remaining_time":0.8848094571},
{"learn":[0.3656055611],"iteration":673,"passed_time":1.823240879,"remaining_time":0.8818642827},
{"learn":[0.3653789202],"iteration":674,"passed_time":1.825709114,"remaining_time":0.8790451287},
{"learn":[0.3652946271],"iteration":675,"passed_time":1.828877864,"remaining_time":0.876562763},
{"learn":[0.3651455484],"iteration":676,"passed_time":1.8316573,"remaining_time":0.873892626},
{"learn":[0.3650285336],"iteration":677,"passed_time":1.834823585,"remaining_time":0.8714058912},
{"learn":[0.3649602546],"iteration":678,"passed_time":1.837815033,"remaining_time":0.8688345003},
{"learn":[0.3647680997],"iteration":679,"passed_time":1.841387684,"remaining_time":0.8665353805},
{"learn":[0.3646928314],"iteration":680,"passed_time":1.843640003,"remaining_time":0.8636140396},
{"learn":[0.364530949],"iteration":681,"passed_time":1.845597143,"remaining_time":0.8605570255},
{"learn":[0.3642827333],"iteration":682,"passed_time":1.847710052,"remaining_time":0.8575755292},
{"learn":[0.3641367548],"iteration":683,"passed_time":1.8499962,"remaining_time":0.8546766071},
{"learn":[0.3638810733],"iteration":684,"passed_time":1.852222184,"remaining_time":0.8517518072},
{"learn":[0.3637789377],"iteration":685,"passed_time":1.855878225,"remaining_time":0.849483619},
{"learn":[0.3635769069],"iteration":686,"passed_time":1.860368472,"remaining_time":0.8475914581},
{"learn":[0.3633963219],"iteration":687,"passed_time":1.862693341,"remaining_time":0.8447097708},
{"learn":[0.363313063],"iteration":688,"passed_time":1.865622443,"remaining_time":0.842102438},
{"learn":[0.3632115806],"iteration":689,"passed_time":1.868453405,"remaining_time":0.8394500807},
{"learn":[0.3631162302],"iteration":690,"passed_time":1.871157399,"remaining_time":0.8367404286},
{"learn":[0.3628654972],"iteration":691,"passed_time":1.873764621,"remaining_time":0.8339877216},
{"learn":[0.362780864],"iteration":692,"passed_time":1.876643196,"remaining_time":0.8313556437},
{"learn":[0.3626837013],"iteration":693,"passed_time":1.878844487,"remaining_time":0.828424226},
{"learn":[0.3625858982],"iteration":694,"passed_time":1.8816197,"remaining_time":0.825746775},
{"learn":[0.3625290967],"iteration":695,"passed_time":1.885186944,"remaining_time":0.8234149869},
{"learn":[0.3624564911],"iteration":696,"passed_time":1.887337942,"remaining_time":0.8204639832},
{"learn":[0.3622838205],"iteration":697,"passed_time":1.890064079,"remaining_time":0.8177641145},
{"learn":[0.3622190376],"iteration":698,"passed_time":1.893028404,"remaining_time":0.8151667376},
{"learn":[0.3621536772],"iteration":699,"passed_time":1.89746386,"remaining_time":0.8131987972},
{"learn":[0.3619824409],"iteration":700,"passed_time":1.900871273,"remaining_time":0.8107853219},
{"learn":[0.3618422146],"iteration":701,"passed_time":1.903623699,"remaining_time":0.8080909717},
{"learn":[0.3617088629],"iteration":702,"passed_time":1.906078582,"remaining_time":0.8052707521},
{"learn":[0.3616505441],"iteration":703,"passed_time":1.908165871,"remaining_time":0.8022970138},
{"learn":[0.3616246094],"iteration":704,"passed_time":1.909627166,"remaining_time":0.7990638497},
{"learn":[0.3614641892],"iteration":705,"passed_time":1.912143452,"remaining_time":0.7962750352},
{"learn":[0.3613340515],"iteration":706,"passed_time":1.915430057,"remaining_time":0.7938062328},
{"learn":[0.3610942799],"iteration":707,"passed_time":1.918147456,"remaining_time":0.7911003632},
{"learn":[0.3610025092],"iteration":708,"passed_time":1.920364313,"remaining_time":0.7881890198},
{"learn":[0.3609203363],"iteration":709,"passed_time":1.923025193,"remaining_time":0.7854609945},
{"learn":[0.3607941671],"iteration":710,"passed_time":1.925994542,"remaining_time":0.782858541},
{"learn":[0.3605238157],"iteration":711,"passed_time":1.928632366,"remaining_time":0.7801209572},
{"learn":[0.3604159309],"iteration":712,"passed_time":1.931294131,"remaining_time":0.7773932897},
{"learn":[0.3602435573],"iteration":713,"passed_time":1.933976415,"remaining_time":0.7746740261},
{"learn":[0.3601699842],"iteration":714,"passed_time":1.936572346,"remaining_time":0.7719204458},
{"learn":[0.3599395922],"iteration":715,"passed_time":1.939596273,"remaining_time":0.7693370694},
{"learn":[0.3597479015],"iteration":716,"passed_time":1.941729264,"remaining_time":0.7664008113},
{"learn":[0.3595780935],"iteration":717,"passed_time":1.943723291,"remaining_time":0.7634122116},
{"learn":[0.3594642962],"iteration":718,"passed_time":1.946093253,"remaining_time":0.760573302},
{"learn":[0.3594000396],"iteration":719,"passed_time":1.948492804,"remaining_time":0.7577472015},
{"learn":[0.359169962],"iteration":720,"passed_time":1.951328763,"remaining_time":0.7550911578},
{"learn":[0.3591244712],"iteration":721,"passed_time":1.952755589,"remaining_time":0.7518920413},
{"learn":[0.3590678846],"iteration":722,"passed_time":1.956313663,"remaining_time":0.7495143632},
{"learn":[0.3589951283],"iteration":723,"passed_time":1.959048024,"remaining_time":0.7468194126},
{"learn":[0.3586951006],"iteration":724,"passed_time":1.961874811,"remaining_time":0.744159411},
{"learn":[0.3586283976],"iteration":725,"passed_time":1.964525243,"remaining_time":0.7414323918},
{"learn":[0.3584640264],"iteration":726,"passed_time":1.966796538,"remaining_time":0.7385632116},
{"learn":[0.3583000359],"iteration":727,"passed_time":1.968911203,"remaining_time":0.7356371527},
{"learn":[0.3580879047],"iteration":728,"passed_time":1.971097382,"remaining_time":0.7327399045},
{"learn":[0.3579460414],"iteration":729,"passed_time":1.97312196,"remaining_time":0.7297848345},
{"learn":[0.3578003852],"iteration":730,"passed_time":1.97584378,"remaining_time":0.7270888875},
{"learn":[0.357677468],"iteration":731,"passed_time":1.978718931,"remaining_time":0.7244490076},
{"learn":[0.3576193858],"iteration":732,"passed_time":1.980665918,"remaining_time":0.7214703957},
{"learn":[0.3574282367],"iteration":733,"passed_time":1.983524899,"remaining_time":0.7188250998},
{"learn":[0.3573553931],"iteration":734,"passed_time":1.98641973,"remaining_time":0.7161921476},
{"learn":[0.3572296972],"iteration":735,"passed_time":1.989152072,"remaining_time":0.7135001996},
{"learn":[0.3569111981],"iteration":736,"passed_time":1.991521846,"remaining_time":0.710678759},
{"learn":[0.3566071748],"iteration":737,"passed_time":1.994344073,"remaining_time":0.7080191697},
{"learn":[0.3565368156],"iteration":738,"passed_time":1.998117269,"remaining_time":0.7056950029},
{"learn":[0.3563807692],"iteration":739,"passed_time":2.000652825,"remaining_time":0.7029320737},
{"learn":[0.3562971518],"iteration":740,"passed_time":2.003432562,"remaining_time":0.700255106},
{"learn":[0.3561996656],"iteration":741,"passed_time":2.005554343,"remaining_time":0.6973490844},
{"learn":[0.3561522269],"iteration":742,"passed_time":2.007478221,"remaining_time":0.6943767199},
{"learn":[0.3561241328],"iteration":743,"passed_time":2.009032591,"remaining_time":0.6912800314},
{"learn":[0.3558633999],"iteration":744,"passed_time":2.010960718,"remaining_time":0.6883154136},
{"learn":[0.3557247338],"iteration":745,"passed_time":2.013106927,"remaining_time":0.6854278278},
{"learn":[0.3555815737],"iteration":746,"passed_time":2.015967505,"remaining_time":0.682784175},
{"learn":[0.3554384691],"iteration":747,"passed_time":2.019080315,"remaining_time":0.6802249191},
{"learn":[0.3553170587],"iteration":748,"passed_time":2.022031185,"remaining_time":0.6776099166},
{"learn":[0.355196657],"iteration":749,"passed_time":2.024643253,"remaining_time":0.6748810843},
{"learn":[0.3548918547],"iteration":750,"passed_time":2.027313054,"remaining_time":0.6721717048},
{"learn":[0.3548316367],"iteration":751,"passed_time":2.029702502,"remaining_time":0.6693699739},
{"learn":[0.3547145165],"iteration":752,"passed_time":2.032105044,"remaining_time":0.6665736333},
{"learn":[0.3546313045],"iteration":753,"passed_time":2.035216622,"remaining_time":0.6640096672},
{"learn":[0.3545032466],"iteration":754,"passed_time":2.037802397,"remaining_time":0.6612736254},
{"learn":[0.3543112709],"iteration":755,"passed_time":2.039941021,"remaining_time":0.6583936628},
{"learn":[0.3542606531],"iteration":756,"passed_time":2.041853698,"remaining_time":0.6554431291},
{"learn":[0.3542299612],"iteration":757,"passed_time":2.043389498,"remaining_time":0.6523750112},
{"learn":[0.3542119595],"iteration":758,"passed_time":2.044324652,"remaining_time":0.6491202122},
{"learn":[0.354086111],"iteration":759,"passed_time":2.046512182,"remaining_time":0.6462670049},
{"learn":[0.3539852566],"iteration":760,"passed_time":2.04857532,"remaining_time":0.6433764802},
{"learn":[0.3538465035],"iteration":761,"passed_time":2.05116548,"remaining_time":0.6406527354},
{"learn":[0.3536294287],"iteration":762,"passed_time":2.053942856,"remaining_time":0.6379874927},
{"learn":[0.353421446],"iteration":763,"passed_time":2.057170032,"remaining_time":0.6354608999},
{"learn":[0.3532668872],"iteration":764,"passed_time":2.059902137,"remaining_time":0.632780395},
{"learn":[0.353082349],"iteration":765,"passed_time":2.062785016,"remaining_time":0.6301458143},
{"learn":[0.3530166243],"iteration":766,"passed_time":2.065019923,"remaining_time":0.6273137444},
{"learn":[0.352849029],"iteration":767,"passed_time":2.066882969,"remaining_time":0.6243708969},
{"learn":[0.3525952764],"iteration":768,"passed_time":2.068770391,"remaining_time":0.6214381797},
{"learn":[0.3525168682],"iteration":769,"passed_time":2.070729964,"remaining_time":0.6185297295},
{"learn":[0.352442188],"iteration":770,"passed_time":2.072575867,"remaining_time":0.6155899786},
{"learn":[0.3523404673],"iteration":771,"passed_time":2.075015921,"remaining_time":0.6128285363},
{"learn":[0.3521342228],"iteration":772,"passed_time":2.077548787,"remaining_time":0.6100951805},
{"learn":[0.3520269106],"iteration":773,"passed_time":2.079612982,"remaining_time":0.6072254961},
{"learn":[0.351790984],"iteration":774,"passed_time":2.081934801,"remaining_time":0.6044326843},
{"learn":[0.3517075839],"iteration":775,"passed_time":2.084140109,"remaining_time":0.6016074541},
{"learn":[0.3515291934],"iteration":776,"passed_time":2.086513534,"remaining_time":0.5988320695},
{"learn":[0.3514939735],"iteration":777,"passed_time":2.089107576,"remaining_time":0.5961206707},
{"learn":[0.351413095],"iteration":778,"passed_time":2.091822233,"remaining_time":0.5934437914},
{"learn":[0.3513516583],"iteration":779,"passed_time":2.094189087,"remaining_time":0.5906687169},
{"learn":[0.3512404825],"iteration":780,"passed_time":2.096225843,"remaining_time":0.5878021251},
{"learn":[0.3510707975],"iteration":781,"passed_time":2.098313885,"remaining_time":0.5849519525},
{"learn":[0.3510070937],"iteration":782,"passed_time":2.100197226,"remaining_time":0.5820469961},
{"learn":[0.3508498262],"iteration":783,"passed_time":2.102156208,"remaining_time":0.579165486},
{"learn":[0.3507397701],"iteration":784,"passed_time":2.104026157,"remaining_time":0.5762619411},
{"learn":[0.3505488856],"iteration":785,"passed_time":2.105924559,"remaining_time":0.5733687731},
{"learn":[0.3503822302],"iteration":786,"passed_time":2.107894513,"remaining_time":0.5704974984},
{"learn":[0.3503042018],"iteration":787,"passed_time":2.109946041,"remaining_time":0.5676504576},
{"learn":[0.3501193158],"iteration":788,"passed_time":2.112043418,"remaining_time":0.5648176947},
{"learn":[0.3500389788],"iteration":789,"passed_time":2.115482166,"remaining_time":0.5623433606},
{"learn":[0.3499522321],"iteration":790,"passed_time":2.118227082,"remaining_time":0.5596832619},
{"learn":[0.3498591517],"iteration":791,"passed_time":2.120779106,"remaining_time":0.5569722905},
{"learn":[0.3497975909],"iteration":792,"passed_time":2.12326897,"remaining_time":0.5542454941},
{"learn":[0.3497386546],"iteration":793,"passed_time":2.125473546,"remaining_time":0.5514452778},
{"learn":[0.3495183868],"iteration":794,"passed_time":2.12741358,"remaining_time":0.5485783446},
{"learn":[0.3494044967],"iteration":795,"passed_time":2.129318437,"remaining_time":0.545704725},
{"learn":[0.3493415432],"iteration":796,"passed_time":2.131174102,"remaining_time":0.5428210071},
{"learn":[0.3492067527],"iteration":797,"passed_time":2.13304219,"remaining_time":0.5399430105},
{"learn":[0.3490541277],"iteration":798,"passed_time":2.135259785,"remaining_time":0.5371554653},
{"learn":[0.348953833],"iteration":799,"passed_time":2.137636705,"remaining_time":0.5344091764},
{"learn":[0.3488960337],"iteration":800,"passed_time":2.139568634,"remaining_time":0.5315532561},
{"learn":[0.3487929357],"iteration":801,"passed_time":2.141723396,"remaining_time":0.5287546539},
{"learn":[0.3486876515],"iteration":802,"passed_time":2.143834603,"remaining_time":0.5259469698},
{"learn":[0.3485157306],"iteration":803,"passed_time":2.146472226,"remaining_time":0.5232693487},
{"learn":[0.3483043681],"iteration":804,"passed_time":2.148778756,"remaining_time":0.5205116241},
{"learn":[0.3482324551],"iteration":805,"passed_time":2.151312661,"remaining_time":0.5178097471},
{"learn":[0.3480111239],"iteration":806,"passed_time":2.153932153,"remaining_time":0.5151287552},
{"learn":[0.3478401049],"iteration":807,"passed_time":2.156876805,"remaining_time":0.5125251815},
{"learn":[0.347750414],"iteration":808,"passed_time":2.158813924,"remaining_time":0.5096828918},
{"learn":[0.3477084308],"iteration":809,"passed_time":2.160980173,"remaining_time":0.5068965838},
{"learn":[0.3475574319],"iteration":810,"passed_time":2.163107184,"remaining_time":0.5041026607},
{"learn":[0.3475155731],"iteration":811,"passed_time":2.164381641,"remaining_time":0.5011129908},
{"learn":[0.347397533],"iteration":812,"passed_time":2.16633802,"remaining_time":0.4982843909},
{"learn":[0.3473102388],"iteration":813,"passed_time":2.168242055,"remaining_time":0.4954459732},
{"learn":[0.3471726596],"iteration":814,"passed_time":2.170206092,"remaining_time":0.4926234688},
{"learn":[0.3470980414],"iteration":815,"passed_time":2.172262892,"remaining_time":0.4898239854},
{"learn":[0.3470591636],"iteration":816,"passed_time":2.174384934,"remaining_time":0.4870409338},
{"learn":[0.3468917986],"iteration":817,"passed_time":2.176712713,"remaining_time":0.4843052736},
{"learn":[0.34684482],"iteration":818,"passed_time":2.179323988,"remaining_time":0.4816332622},
{"learn":[0.3467492193],"iteration":819,"passed_time":2.181748278,"remaining_time":0.4789203537},
{"learn":[0.3466586134],"iteration":820,"passed_time":2.184183428,"remaining_time":0.476210516},
{"learn":[0.3465678604],"iteration":821,"passed_time":2.186685507,"remaining_time":0.4735158397},
{"learn":[0.3462972671],"iteration":822,"passed_time":2.189016803,"remaining_time":0.4707849018},
{"learn":[0.3461064493],"iteration":823,"passed_time":2.191110805,"remaining_time":0.4680042496},
{"learn":[0.346068202],"iteration":824,"passed_time":2.193169294,"remaining_time":0.465217729},
{"learn":[0.3459330036],"iteration":825,"passed_time":2.195897283,"remaining_time":0.4625740039},
{"learn":[0.3458906029],"iteration":826,"passed_time":2.198015984,"remaining_time":0.4598026182},
{"learn":[0.3456898258],"iteration":827,"passed_time":2.200442306,"remaining_time":0.4570967109},
{"learn":[0.3455773222],"iteration":828,"passed_time":2.202476984,"remaining_time":0.4543106928},
{"learn":[0.3455653343],"iteration":829,"passed_time":2.203498196,"remaining_time":0.4513189077},
{"learn":[0.3454919413],"iteration":830,"passed_time":2.206091916,"remaining_time":0.4486516653},
{"learn":[0.3454350053],"iteration":831,"passed_time":2.208757331,"remaining_time":0.4459990764},
{"learn":[0.3454010764],"iteration":832,"passed_time":2.210359796,"remaining_time":0.4431333564},
{"learn":[0.3453306429],"iteration":833,"passed_time":2.213289033,"remaining_time":0.4405347476},
{"learn":[0.3452732623],"iteration":834,"passed_time":2.215936912,"remaining_time":0.437879749},
{"learn":[0.3452084964],"iteration":835,"passed_time":2.219116919,"remaining_time":0.4353291565},
{"learn":[0.3450982918],"iteration":836,"passed_time":2.221328898,"remaining_time":0.4325885428},
{"learn":[0.3450315692],"iteration":837,"passed_time":2.223666385,"remaining_time":0.4298734539},
{"learn":[0.3448202249],"iteration":838,"passed_time":2.22569825,"remaining_time":0.4271006176},
{"learn":[0.344740896],"iteration":839,"passed_time":2.228004582,"remaining_time":0.4243818252},
{"learn":[0.3445802196],"iteration":840,"passed_time":2.230608597,"remaining_time":0.4217202937},
{"learn":[0.3445089176],"iteration":841,"passed_time":2.232700374,"remaining_time":0.418962778},
{"learn":[0.3444557221],"iteration":842,"passed_time":2.236011309,"remaining_time":0.4164338975},
{"learn":[0.3443737886],"iteration":843,"passed_time":2.238825834,"remaining_time":0.41381141},
{"learn":[0.3443455304],"iteration":844,"passed_time":2.241186767,"remaining_time":0.4111052649},
{"learn":[0.3442940492],"iteration":845,"passed_time":2.243699853,"remaining_time":0.4084276329},
{"learn":[0.3441512106],"iteration":846,"passed_time":2.246614653,"remaining_time":0.4058229539},
{"learn":[0.3440044718],"iteration":847,"passed_time":2.248961953,"remaining_time":0.4031158217},
{"learn":[0.3439424086],"iteration":848,"passed_time":2.251914553,"remaining_time":0.4005171938},
{"learn":[0.3437315936],"iteration":849,"passed_time":2.254232634,"remaining_time":0.3978057589},
{"learn":[0.3436966441],"iteration":850,"passed_time":2.25682695,"remaining_time":0.395143614},
{"learn":[0.3435924469],"iteration":851,"passed_time":2.259078546,"remaining_time":0.3924220949},
{"learn":[0.3434977772],"iteration":852,"passed_time":2.261253763,"remaining_time":0.3896885149},
{"learn":[0.3434122112],"iteration":853,"passed_time":2.263399301,"remaining_time":0.3869511685},
{"learn":[0.3433187169],"iteration":854,"passed_time":2.265360046,"remaining_time":0.3841838674},
{"learn":[0.3430567512],"iteration":855,"passed_time":2.26768101,"remaining_time":0.3814790484},
{"learn":[0.3430023481],"iteration":856,"passed_time":2.270001222,"remaining_time":0.3787749997},
{"learn":[0.3428537085],"iteration":857,"passed_time":2.272341099,"remaining_time":0.3760751003},
{"learn":[0.3427490613],"iteration":858,"passed_time":2.274735634,"remaining_time":0.3733850109},
{"learn":[0.3426133662],"iteration":859,"passed_time":2.278024422,"remaining_time":0.370841185},
{"learn":[0.3423614509],"iteration":860,"passed_time":2.280400619,"remaining_time":0.3681482997},
{"learn":[0.3421636276],"iteration":861,"passed_time":2.28317694,"remaining_time":0.3655202062},
{"learn":[0.3421402081],"iteration":862,"passed_time":2.28582356,"remaining_time":0.3628711793},
{"learn":[0.3420514749],"iteration":863,"passed_time":2.287895476,"remaining_time":0.3601316953},
{"learn":[0.3419597355],"iteration":864,"passed_time":2.289806041,"remaining_time":0.3573685728},
{"learn":[0.341726427],"iteration":865,"passed_time":2.291972621,"remaining_time":0.3546470337},
{"learn":[0.3416275748],"iteration":866,"passed_time":2.294127674,"remaining_time":0.3519250065},
{"learn":[0.3414247233],"iteration":867,"passed_time":2.296464657,"remaining_time":0.3492319524},
{"learn":[0.3413134238],"iteration":868,"passed_time":2.298792385,"remaining_time":0.3465383227},
{"learn":[0.3412401459],"iteration":869,"passed_time":2.300886103,"remaining_time":0.3438105671},
{"learn":[0.3411129447],"iteration":870,"passed_time":2.303261344,"remaining_time":0.3411259625},
{"learn":[0.3410725248],"iteration":871,"passed_time":2.305940187,"remaining_time":0.338486633},
{"learn":[0.3409947246],"iteration":872,"passed_time":2.308688417,"remaining_time":0.3358573069},
{"learn":[0.3408971784],"iteration":873,"passed_time":2.311434469,"remaining_time":0.3332273948},
{"learn":[0.340735699],"iteration":874,"passed_time":2.314189164,"remaining_time":0.3305984521},
{"learn":[0.3406956276],"iteration":875,"passed_time":2.317946483,"remaining_time":0.328111146},
{"learn":[0.3406214741],"iteration":876,"passed_time":2.320048339,"remaining_time":0.3253887636},
{"learn":[0.3404551819],"iteration":877,"passed_time":2.322024575,"remaining_time":0.3226503396},
{"learn":[0.3402865332],"iteration":878,"passed_time":2.323937539,"remaining_time":0.3199049399},
{"learn":[0.3402170147],"iteration":879,"passed_time":2.32586164,"remaining_time":0.3171629509},
{"learn":[0.3401633309],"iteration":880,"passed_time":2.32780727,"remaining_time":0.3144257267},
{"learn":[0.3399360825],"iteration":881,"passed_time":2.329617685,"remaining_time":0.3116722072},
{"learn":[0.3398269474],"iteration":882,"passed_time":2.331651013,"remaining_time":0.3089503607},
{"learn":[0.3397405597],"iteration":883,"passed_time":2.333676652,"remaining_time":0.3062290629},
{"learn":[0.3395546108],"iteration":884,"passed_time":2.335907924,"remaining_time":0.303536058},
{"learn":[0.3394320092],"iteration":885,"passed_time":2.338169388,"remaining_time":0.3008479799},
{"learn":[0.3393295332],"iteration":886,"passed_time":2.340558101,"remaining_time":0.2981770749},
{"learn":[0.3392255148],"iteration":887,"passed_time":2.343111379,"remaining_time":0.2955275613},
{"learn":[0.3391481606],"iteration":888,"passed_time":2.345613438,"remaining_time":0.2928718691},
{"learn":[0.3391052203],"iteration":889,"passed_time":2.348286559,"remaining_time":0.2902376646},
{"learn":[0.338968956],"iteration":890,"passed_time":2.350349058,"remaining_time":0.2875286726},
{"learn":[0.3389424757],"iteration":891,"passed_time":2.352132091,"remaining_time":0.2847872935},
{"learn":[0.3387392633],"iteration":892,"passed_time":2.35403784,"remaining_time":0.2820627647},
{"learn":[0.3386722952],"iteration":893,"passed_time":2.356640334,"remaining_time":0.2794226794},
{"learn":[0.3386499525],"iteration":894,"passed_time":2.358739797,"remaining_time":0.2767236634},
{"learn":[0.338442439],"iteration":895,"passed_time":2.360696786,"remaining_time":0.2740094484},
{"learn":[0.3382837633],"iteration":896,"passed_time":2.362641159,"remaining_time":0.2712954731},
{"learn":[0.3381716397],"iteration":897,"passed_time":2.364512716,"remaining_time":0.268574941},
{"learn":[0.3380928149],"iteration":898,"passed_time":2.366649232,"remaining_time":0.265886065},
{"learn":[0.3380269011],"iteration":899,"passed_time":2.368699593,"remaining_time":0.2631888437},
{"learn":[0.3379942452],"iteration":900,"passed_time":2.371003009,"remaining_time":0.2605208634},
{"learn":[0.3378894029],"iteration":901,"passed_time":2.373567338,"remaining_time":0.257882039},
{"learn":[0.3378298566],"iteration":902,"passed_time":2.376400805,"remaining_time":0.2552722902},
{"learn":[0.33778241],"iteration":903,"passed_time":2.379135675,"remaining_time":0.2526515761},
{"learn":[0.337748979],"iteration":904,"passed_time":2.38135376,"remaining_time":0.2499763615},
{"learn":[0.3376636203],"iteration":905,"passed_time":2.383303134,"remaining_time":0.2472742766},
{"learn":[0.3375686123],"iteration":906,"passed_time":2.385233982,"remaining_time":0.2445719519},
{"learn":[0.3374520904],"iteration":907,"passed_time":2.387117861,"remaining_time":0.2418665674},
{"learn":[0.3373939019],"iteration":908,"passed_time":2.389000625,"remaining_time":0.2391628789},
{"learn":[0.3373126455],"iteration":909,"passed_time":2.391130212,"remaining_time":0.2364854055},
{"learn":[0.3372612925],"iteration":910,"passed_time":2.393232441,"remaining_time":0.2338064624},
{"learn":[0.3371954784],"iteration":911,"passed_time":2.395798369,"remaining_time":0.2311735269},
{"learn":[0.33713301],"iteration":912,"passed_time":2.398246655,"remaining_time":0.228529528},
{"learn":[0.3369376426],"iteration":913,"passed_time":2.400319435,"remaining_time":0.2258506251},
{"learn":[0.3368483095],"iteration":914,"passed_time":2.402513484,"remaining_time":0.2231843127},
{"learn":[0.3367634207],"iteration":915,"passed_time":2.404866411,"remaining_time":0.220533601},
{"learn":[0.3365790259],"iteration":916,"passed_time":2.407306211,"remaining_time":0.2178914019},
{"learn":[0.3364343042],"iteration":917,"passed_time":2.40985826,"remaining_time":0.2152596703},
{"learn":[0.3363716908],"iteration":918,"passed_time":2.412563585,"remaining_time":0.2126416217},
{"learn":[0.3363386517],"iteration":919,"passed_time":2.414548994,"remaining_time":0.2099607821},
{"learn":[0.3362997489],"iteration":920,"passed_time":2.416711789,"remaining_time":0.2072966681},
{"learn":[0.3361027198],"iteration":921,"passed_time":2.418550145,"remaining_time":0.2046061945},
{"learn":[0.3359262007],"iteration":922,"passed_time":2.420451826,"remaining_time":0.2019228501},
{"learn":[0.3356683838],"iteration":923,"passed_time":2.42237228,"remaining_time":0.1992427416},
{"learn":[0.3355861032],"iteration":924,"passed_time":2.42438347,"remaining_time":0.1965716327},
{"learn":[0.335554761],"iteration":925,"passed_time":2.426460483,"remaining_time":0.1939072093},
{"learn":[0.3354594753],"iteration":926,"passed_time":2.428029332,"remaining_time":0.1912040358},
{"learn":[0.3353149008],"iteration":927,"passed_time":2.430028281,"remaining_time":0.188536677},
{"learn":[0.3352219501],"iteration":928,"passed_time":2.431653844,"remaining_time":0.1858422206},
{"learn":[0.335138754],"iteration":929,"passed_time":2.433865449,"remaining_time":0.1831941736},
{"learn":[0.3350379307],"iteration":930,"passed_time":2.436847841,"remaining_time":0.1806041902},
{"learn":[0.3349632306],"iteration":931,"passed_time":2.439636585,"remaining_time":0.1779992358},
{"learn":[0.3349153388],"iteration":932,"passed_time":2.442136693,"remaining_time":0.1753731601},
{"learn":[0.3348046215],"iteration":933,"passed_time":2.444752604,"remaining_time":0.1727555373},
{"learn":[0.3346225855],"iteration":934,"passed_time":2.446776624,"remaining_time":0.1700967707},
{"learn":[0.3345419045],"iteration":935,"passed_time":2.448766079,"remaining_time":0.1674369969},
{"learn":[0.3344939017],"iteration":936,"passed_time":2.45065389,"remaining_time":0.1647718197},
{"learn":[0.3344483238],"iteration":937,"passed_time":2.45260999,"remaining_time":0.1621128138},
{"learn":[0.3344423028],"iteration":938,"passed_time":2.453455123,"remaining_time":0.1593831337},
{"learn":[0.3343997126],"iteration":939,"passed_time":2.455672081,"remaining_time":0.1567450264},
{"learn":[0.3341684586],"iteration":940,"passed_time":2.457973847,"remaining_time":0.1541131317},
{"learn":[0.3340719169],"iteration":941,"passed_time":2.460031931,"remaining_time":0.1514669342},
{"learn":[0.3340179695],"iteration":942,"passed_time":2.462166221,"remaining_time":0.1488265903},
{"learn":[0.3339771482],"iteration":943,"passed_time":2.463806906,"remaining_time":0.1461580368},
{"learn":[0.3339290654],"iteration":944,"passed_time":2.46603668,"remaining_time":0.1435259443},
{"learn":[0.3338492427],"iteration":945,"passed_time":2.468354742,"remaining_time":0.1408997421},
{"learn":[0.3337854422],"iteration":946,"passed_time":2.470787264,"remaining_time":0.1382805966},
{"learn":[0.3336849437],"iteration":947,"passed_time":2.473267381,"remaining_time":0.1356644555},
{"learn":[0.3336137783],"iteration":948,"passed_time":2.476050842,"remaining_time":0.133064903},
{"learn":[0.3335641915],"iteration":949,"passed_time":2.478847813,"remaining_time":0.1304656744},
{"learn":[0.3335266029],"iteration":950,"passed_time":2.480802147,"remaining_time":0.1278226133},
{"learn":[0.333422049],"iteration":951,"passed_time":2.482760811,"remaining_time":0.1251812174},
{"learn":[0.3333510922],"iteration":952,"passed_time":2.48472499,"remaining_time":0.1225415263},
{"learn":[0.3332864775],"iteration":953,"passed_time":2.48657067,"remaining_time":0.1198975375},
{"learn":[0.3331773768],"iteration":954,"passed_time":2.48857964,"remaining_time":0.117262915},
{"learn":[0.3331411979],"iteration":955,"passed_time":2.490466093,"remaining_time":0.1146239624},
{"learn":[0.3329395093],"iteration":956,"passed_time":2.49240037,"remaining_time":0.1119887313},
{"learn":[0.3328906514],"iteration":957,"passed_time":2.494630082,"remaining_time":0.1093679159},
{"learn":[0.3328182443],"iteration":958,"passed_time":2.497209126,"remaining_time":0.1067628511},
{"learn":[0.3327550286],"iteration":959,"passed_time":2.499808177,"remaining_time":0.104158674},
{"learn":[0.3326940442],"iteration":960,"passed_time":2.502241023,"remaining_time":0.1015477627},
{"learn":[0.3326422191],"iteration":961,"passed_time":2.50469002,"remaining_time":0.09893785941},
{"learn":[0.332574308],"iteration":962,"passed_time":2.507384555,"remaining_time":0.09633772433},
{"learn":[0.3324856524],"iteration":963,"passed_time":2.50975602,"remaining_time":0.09372532854},
{"learn":[0.3324514677],"iteration":964,"passed_time":2.511758898,"remaining_time":0.09110006366},
{"learn":[0.3323367767],"iteration":965,"passed_time":2.513685424,"remaining_time":0.0884734},
{"learn":[0.3322287289],"iteration":966,"passed_time":2.515940165,"remaining_time":0.08585938517},
{"learn":[0.3321443744],"iteration":967,"passed_time":2.518489066,"remaining_time":0.08325583691},
{"learn":[0.3320229333],"iteration":968,"passed_time":2.520429364,"remaining_time":0.08063293115},
{"learn":[0.3318551575],"iteration":969,"passed_time":2.522424499,"remaining_time":0.07801312883},
{"learn":[0.3317103852],"iteration":970,"passed_time":2.524345814,"remaining_time":0.07539240846},
{"learn":[0.3316952622],"iteration":971,"passed_time":2.525657949,"remaining_time":0.07275557879},
{"learn":[0.3315887022],"iteration":972,"passed_time":2.527756675,"remaining_time":0.07014329932},
{"learn":[0.3314803463],"iteration":973,"passed_time":2.529875003,"remaining_time":0.06753259761},
{"learn":[0.3314357299],"iteration":974,"passed_time":2.53251724,"remaining_time":0.06493633949},
{"learn":[0.3312879574],"iteration":975,"passed_time":2.535163313,"remaining_time":0.06234008148},
{"learn":[0.3310936475],"iteration":976,"passed_time":2.537942079,"remaining_time":0.05974684527},
{"learn":[0.3309833602],"iteration":977,"passed_time":2.541152633,"remaining_time":0.05716294266},
{"learn":[0.3309163996],"iteration":978,"passed_time":2.543350171,"remaining_time":0.05455603023},
{"learn":[0.3308401727],"iteration":979,"passed_time":2.545278627,"remaining_time":0.05194446177},
{"learn":[0.3307625649],"iteration":980,"passed_time":2.547271768,"remaining_time":0.04933553882},
{"learn":[0.3305622899],"iteration":981,"passed_time":2.549154903,"remaining_time":0.04672585363},
{"learn":[0.3304791324],"iteration":982,"passed_time":2.551080208,"remaining_time":0.04411837593},
{"learn":[0.3303744353],"iteration":983,"passed_time":2.552997258,"remaining_time":0.04151215054},
{"learn":[0.330328921],"iteration":984,"passed_time":2.554871824,"remaining_time":0.03890667752},
{"learn":[0.3302299879],"iteration":985,"passed_time":2.557240338,"remaining_time":0.03630970054},
{"learn":[0.3301767413],"iteration":986,"passed_time":2.55965058,"remaining_time":0.03371373611},
{"learn":[0.3301291977],"iteration":987,"passed_time":2.561731008,"remaining_time":0.03111414179},
{"learn":[0.3301236631],"iteration":988,"passed_time":2.562826698,"remaining_time":0.02850464477},
{"learn":[0.3299853527],"iteration":989,"passed_time":2.565100075,"remaining_time":0.02591010176},
{"learn":[0.3298404503],"iteration":990,"passed_time":2.56739762,"remaining_time":0.02331642641},
{"learn":[0.3298011992],"iteration":991,"passed_time":2.569682887,"remaining_time":0.02072324909},
{"learn":[0.3296452172],"iteration":992,"passed_time":2.572280223,"remaining_time":0.01813289181},
{"learn":[0.3295104733],"iteration":993,"passed_time":2.574442977,"remaining_time":0.01553989724},
{"learn":[0.3294241394],"iteration":994,"passed_time":2.576631626,"remaining_time":0.01294789762},
{"learn":[0.3293782708],"iteration":995,"passed_time":2.578774574,"remaining_time":0.01035652439},
{"learn":[0.3293130981],"iteration":996,"passed_time":2.580663818,"remaining_time":0.007765287315},
{"learn":[0.3292057805],"iteration":997,"passed_time":2.582588502,"remaining_time":0.00517552806},
{"learn":[0.32908711],"iteration":998,"passed_time":2.584538205,"remaining_time":0.00258712533},
{"learn":[0.3290222911],"iteration":999,"passed_time":2.586484606,"remaining_time":0}
]}